Workbook
Name Slicer_Product_Type: #N/A
Name Slicer_Sales_Channel: #N/A
Name Slicer_State: #N/A
Name Slicer_Supplier: #N/A

Sheet Poultry dataset
A1: Order_ID | B1: Date | C1: Delivery_Date | D1: Product_Type | E1: Quantity_Ordered | F1: Unit_Selling_Price_NGN | G1: Discount_Percent | H1: Revenue_NGN | I1: Supplier | J1: Unit_Purchase_Cost_NGN | K1: Procurement_Cost_NGN | L1: Transport_Cost_NGN | M1: Handling_Cost_NGN | N1: Other_Cost_NGN | O1: Total_Cost_NGN | P1: Gross_Profit_NGN | Q1: Net_Profit_NGN | R1: Payment_Status | S1: Payment_Received_NGN | T1: Balance_Due_NGN | U1: Delivery_Status | V1: Sales_Channel | W1: Customer_Type | X1: State | Y1: Region | Z1: Estimated_Mortality_Percent | AA1: Computed_Net_Profit_NGN | AB1: Profit_Margin_Percent | AC1: Net_Profit_Reconciliation_NGN | AD1: Order_Year | AE1: Order_Month_Number | AF1: Order_Month | AG1: Order_YearMonth
A2: FZ00001 | B2: 45500 | C2: 45513 | D2: Broiler DOC | E2: 200 | F2: 808.71 | G2: 0.48 | H2: 160965.64 | I2: Farm Support | J2: 704.95 | K2: 140990 | L2: 3237.59 | M2: 588.73 | N2: 1046.45 | O2: 145862.77 | P2: 19975.64 | Q2: 15102.87 | R2: Paid | S2: 160965.64 | T2: 0 | U2: Delivered | V2: WhatsApp | W2: Commercial Farm | X2: Gombe | Y2: North East | Z2: 0.69 | AA2: =ROUND(H2-O2,2) -> 15102.87 | AB2: =AA2/H2 -> 0.09382667 | AC2: =ROUND(AA2-Q2,2) -> 0 | AD2: 2024 | AE2: 7 | AF2: July | AG2: 2024-07
A3: FZ00002 | B3: 45415 | C3: 45416 | D3: Pullet DOC | E3: 300 | F3: 1206.47 | G3: 2.13 | H3: 354231.66 | I3: AgroPlus NG | J3: 977.68 | K3: 293304 | L3: 7055.13 | M3: 1080.55 | N3: 2583.9 | O3: 304023.58 | P3: 60927.66 | Q3: 50208.08 | R3: Paid | S3: 354231.66 | T3: 0 | U3: Collected | V3: Phone Call | W3: Smallholder Farmer | X3: Kaduna | Y3: North West | Z3: 0.11 | AA3: =ROUND(H3-O3,2) -> 50208.08 | AB3: =AA3/H3 -> 0.14173798 | AC3: =ROUND(AA3-Q3,2) -> 0 | AD3: 2024 | AE3: 5 | AF3: May | AG3: 2024-05
A4: FZ00003 | B4: 45519 | C4: 45520 | D4: Broiler DOC | E4: 250 | F4: 901.18 | G4: 1.18 | H4: 222636.52 | I4: CHI FARMS | J4: 671.24 | K4: 167810 | L4: 5685.82 | M4: 1276.01 | N4: 6421.4 | O4: 181193.23 | P4: 54826.52 | Q4: 41443.29 | R4: Paid | S4: 222636.52 | T4: 0 | U4: Collected | V4: Walk-in | W4: Agro-dealer | X4: Enugu | Y4: South East | Z4: 0.33 | AA4: =ROUND(H4-O4,2) -> 41443.29 | AB4: =AA4/H4 -> 0.18614776 | AC4: =ROUND(AA4-Q4,2) -> 0 | AD4: 2024 | AE4: 8 | AF4: August | AG4: 2024-08
A5: FZ00004 | B5: 45873 | C5: 45885 | D5: Cockerel DOC | E5: 200 | F5: 749.22 | G5: 1.2 | H5: 148045.87 | I5: Farm Support | J5: 608.83 | K5: 121766 | L5: 1885.03 | M5: 1055.04 | N5: 5105.53 | O5: 129811.6 | P5: 26279.87 | Q5: 18234.27 | R5: Part-paid | S5: 76965.99 | T5: 71079.88 | U5: Collected | V5: Phone Call | W5: Smallholder Farmer | X5: Delta | Y5: South South | Z5: 1.53 | AA5: =ROUND(H5-O5,2) -> 18234.27 | AB5: =AA5/H5 -> 0.12316635 | AC5: =ROUND(AA5-Q5,2) -> 0 | AD5: 2025 | AE5: 8 | AF5: August | AG5: 2025-08
A6: FZ00005 | B6: 45870 | C6: 45872 | D6: Cockerel DOC | E6: 500 | F6: 758.41 | G6: 2.98 | H6: 367904.69 | I6: Farm Support | J6: 602.65 | K6: 301325 | L6: 2699.99 | M6: 1770.62 | N6: 3487.18 | O6: 309282.79 | P6: 66579.69 | Q6: 58621.9 | R6: Paid | S6: 367904.69 | T6: 0 | U6: Delivered | V6: WhatsApp | W6: Commercial Farm | X6: Jigawa | Y6: North West | Z6: 0.06 | AA6: =ROUND(H6-O6,2) -> 58621.9 | AB6: =AA6/H6 -> 0.15933991 | AC6: =ROUND(AA6-Q6,2) -> 0 | AD6: 2025 | AE6: 8 | AF6: August | AG6: 2025-08
A7: FZ00006 | B7: 45787 | D7: Noiler DOC | E7: 150 | F7: 994.92 | G7: 2.22 | H7: 145924.92 | I7: AgroPlus NG | J7: 781.98 | K7: 117297 | L7: 1733.25 | M7: 563.97 | N7: 7560.43 | O7: 127154.65 | P7: 28627.92 | Q7: 18770.27 | R7: Paid | S7: 145924.92 | T7: 0 | U7: Pending | V7: WhatsApp | W7: Distributor | X7: Kogi | Y7: North Central | Z7: 2.25 | AA7: =ROUND(H7-O7,2) -> 18770.27 | AB7: =AA7/H7 -> 0.12862964 | AC7: =ROUND(AA7-Q7,2) -> 0 | AD7: 2025 | AE7: 5 | AF7: May | AG7: 2025-05
A8: FZ00007 | B8: 45628 | D8: Broiler DOC | E8: 250 | F8: 974.17 | G8: 1.76 | H8: 239256.15 | I8: PAN Industries | J8: 727.3 | K8: 181825 | L8: 5720.86 | M8: 563.44 | N8: 510.45 | O8: 188619.75 | P8: 57431.15 | Q8: 50636.4 | R8: Paid | S8: 239256.15 | T8: 0 | U8: Pending | V8: Reseller | W8: Agro-dealer | X8: Ebonyi | Y8: South East | Z8: 1.25 | AA8: =ROUND(H8-O8,2) -> 50636.4 | AB8: =AA8/H8 -> 0.21164095 | AC8: =ROUND(AA8-Q8,2) -> 0 | AD8: 2024 | AE8: 12 | AF8: December | AG8: 2024-12
A9: FZ00008 | B9: 45318 | C9: 45331 | D9: Pullet DOC | E9: 500 | F9: 1181.27 | G9: 3.64 | H9: 569135.89 | I9: CHI FARMS | J9: 970.22 | K9: 485110 | L9: 7413.03 | M9: 1134.39 | N9: 6338.15 | O9: 499995.57 | P9: 84025.89 | Q9: 69140.32 | R9: Paid | S9: 569135.89 | T9: 0 | U9: Delivered | V9: Social Media | W9: Smallholder Farmer | X9: Ekiti | Y9: South West | Z9: 1.98 | AA9: =ROUND(H9-O9,2) -> 69140.32 | AB9: =AA9/H9 -> 0.12148297 | AC9: =ROUND(AA9-Q9,2) -> 0 | AD9: 2024 | AE9: 1 | AF9: January | AG9: 2024-01
A10: FZ00009 | B10: 45746 | C10: 45756 | D10: Broiler DOC | E10: 750 | F10: 836.85 | G10: 2.67 | H10: 610879.58 | I10: PAN Industries | J10: 673.75 | K10: 505312.5 | L10: 17584.67 | M10: 2579.18 | N10: 5762.05 | O10: 531238.4 | P10: 105567.08 | Q10: 79641.18 | R10: Paid | S10: 610879.58 | T10: 0 | U10: Delivered | V10: Phone Call | W10: Agro-dealer | X10: Enugu | Y10: South East | Z10: 2.01 | AA10: =ROUND(H10-O10,2) -> 79641.18 | AB10: =AA10/H10 -> 0.13037132 | AC10: =ROUND(AA10-Q10,2) -> 0 | AD10: 2025 | AE10: 3 | AF10: March | AG10: 2025-03
A11: FZ00010 | B11: 45779 | C11: 45788 | D11: Pullet DOC | E11: 300 | F11: 1318.81 | G11: 0.21 | H11: 394812.15 | I11: AgroPlus NG | J11: 1052.84 | K11: 315852 | L11: 4252.58 | M11: 1554.06 | N11: 11598.95 | O11: 333257.59 | P11: 78960.15 | Q11: 61554.56 | R11: Paid | S11: 394812.15 | T11: 0 | U11: Delivered | V11: WhatsApp | W11: Smallholder Farmer | X11: Oyo | Y11: South West | Z11: 1.45 | AA11: =ROUND(H11-O11,2) -> 61554.56 | AB11: =AA11/H11 -> 0.15590847 | AC11: =ROUND(AA11-Q11,2) -> 0 | AD11: 2025 | AE11: 5 | AF11: May | AG11: 2025-05
A12: FZ00011 | B12: 45818 | C12: 45818 | D12: Broiler DOC | E12: 200 | F12: 823.5 | G12: 2.33 | H12: 160862.49 | I12: CHI FARMS | J12: 718.26 | K12: 143652 | L12: 2326.27 | M12: 502.84 | N12: 3897.48 | O12: 150378.59 | P12: 17210.49 | Q12: 10483.9 | R12: Paid | S12: 160862.49 | T12: 0 | U12: Delivered | V12: WhatsApp | W12: Smallholder Farmer | X12: Katsina | Y12: North West | Z12: 1.79 | AA12: =ROUND(H12-O12,2) -> 10483.9 | AB12: =AA12/H12 -> 0.065173056 | AC12: =ROUND(AA12-Q12,2) -> 0 | AD12: 2025 | AE12: 6 | AF12: June | AG12: 2025-06
A13: FZ00012 | B13: 45638 | C13: 45643 | D13: Pullet DOC | E13: 200 | F13: 1396.14 | G13: 2.4 | H13: 272526.53 | I13: AgroPlus NG | J13: 1049.81 | K13: 209962 | L13: 3616.53 | M13: 816.72 | N13: 6360.06 | O13: 220755.31 | P13: 62564.53 | Q13: 51771.22 | R13: Paid | S13: 272526.53 | T13: 0 | U13: Delivered | V13: Referral | W13: Agro-dealer | X13: Ebonyi | Y13: South East | Z13: 1.66 | AA13: =ROUND(H13-O13,2) -> 51771.22 | AB13: =AA13/H13 -> 0.18996763 | AC13: =ROUND(AA13-Q13,2) -> 0 | AD13: 2024 | AE13: 12 | AF13: December | AG13: 2024-12
A14: FZ00013 | B14: 45309 | C14: 45323 | D14: Pullet DOC | E14: 100 | F14: 1284.14 | G14: 0.74 | H14: 127463.74 | I14: AgroPlus NG | J14: 983.7 | K14: 98370 | L14: 914.24 | M14: 405.52 | N14: 5571.93 | O14: 105261.69 | P14: 29093.74 | Q14: 22202.05 | R14: Paid | S14: 127463.74 | T14: 0 | U14: Collected | V14: Phone Call | W14: Smallholder Farmer | X14: Lagos | Y14: South West | Z14: 1.45 | AA14: =ROUND(H14-O14,2) -> 22202.05 | AB14: =AA14/H14 -> 0.17418326 | AC14: =ROUND(AA14-Q14,2) -> 0 | AD14: 2024 | AE14: 1 | AF14: January | AG14: 2024-01
A15: FZ00014 | B15: 45673 | D15: Noiler DOC | E15: 100 | F15: 947.09 | G15: 1.98 | H15: 0 | I15: CHI FARMS | J15: 714.98 | K15: 0 | L15: 0 | M15: 0 | N15: 0 | O15: 0 | P15: 0 | Q15: 0 | R15: Paid | S15: 0 | T15: 0 | U15: Cancelled | V15: Reseller | W15: Agro-dealer | X15: Ekiti | Y15: South West | Z15: 2.09 | AA15: =ROUND(H15-O15,2) -> 0 | AB15: =AA15/H15 -> #DIV/0! | AC15: =ROUND(AA15-Q15,2) -> 0 | AD15: 2025 | AE15: 1 | AF15: January | AG15: 2025-01
A16: FZ00015 | B16: 45382 | C16: 45392 | D16: Broiler DOC | E16: 250 | F16: 897.32 | G16: 1.54 | H16: 220875.32 | I16: Farm Support | J16: 734.71 | K16: 183677.5 | L16: 4398.8 | M16: 554.63 | N16: 531.3 | O16: 189162.23 | P16: 37197.82 | Q16: 31713.09 | R16: Paid | S16: 220875.32 | T16: 0 | U16: Delivered | V16: WhatsApp | W16: Smallholder Farmer | X16: Jigawa | Y16: North West | Z16: 1.59 | AA16: =ROUND(H16-O16,2) -> 31713.09 | AB16: =AA16/H16 -> 0.14357915 | AC16: =ROUND(AA16-Q16,2) -> 0 | AD16: 2024 | AE16: 3 | AF16: March | AG16: 2024-03
A17: FZ00016 | B17: 45682 | C17: 45691 | D17: Broiler DOC | E17: 300 | F17: 827.26 | G17: 1.47 | H17: 244529.78 | I17: AgroPlus NG | J17: 748.68 | K17: 224604 | L17: 2951.24 | M17: 1384.84 | N17: 6632.79 | O17: 235572.87 | P17: 19925.78 | Q17: 8956.91 | R17: Paid | S17: 244529.78 | T17: 0 | U17: Delivered | V17: Social Media | W17: Commercial Farm | X17: Kogi | Y17: North Central | Z17: 2.47 | AA17: =ROUND(H17-O17,2) -> 8956.91 | AB17: =AA17/H17 -> 0.036629117 | AC17: =ROUND(AA17-Q17,2) -> 0 | AD17: 2025 | AE17: 1 | AF17: January | AG17: 2025-01
A18: FZ00017 | B18: 45478 | C18: 45487 | D18: Broiler DOC | E18: 50 | F18: 831.37 | G18: 0.28 | H18: 41452.11 | I18: CHI FARMS | J18: 648.63 | K18: 32431.5 | L18: 1170.22 | M18: 257.65 | N18: 9685.54 | O18: 43544.91 | P18: 9020.61 | Q18: -2092.8 | R18: Paid | S18: 41452.11 | T18: 0 | U18: Delivered | V18: WhatsApp | W18: Distributor | X18: Ogun | Y18: South West | Z18: 1.63 | AA18: =ROUND(H18-O18,2) -> -2092.8 | AB18: =AA18/H18 -> -0.050487177 | AC18: =ROUND(AA18-Q18,2) -> 0 | AD18: 2024 | AE18: 7 | AF18: July | AG18: 2024-07
A19: FZ00018 | B19: 45415 | C19: 45422 | D19: Broiler DOC | E19: 500 | F19: 816.16 | G19: 2.04 | H19: 399755.17 | I19: AgroPlus NG | J19: 737.65 | K19: 368825 | L19: 6247.5 | M19: 2228.46 | N19: 4425.55 | O19: 381726.51 | P19: 30930.17 | Q19: 18028.66 | R19: Paid | S19: 399755.17 | T19: 0 | U19: Collected | V19: Referral | W19: Smallholder Farmer | X19: Anambra | Y19: South East | Z19: 0.42 | AA19: =ROUND(H19-O19,2) -> 18028.66 | AB19: =AA19/H19 -> 0.045099254 | AC19: =ROUND(AA19-Q19,2) -> 0 | AD19: 2024 | AE19: 5 | AF19: May | AG19: 2024-05
A20: FZ00019 | B20: 45606 | C20: 45609 | D20: Broiler DOC | E20: 1000 | F20: 874.45 | G20: 1.21 | H20: 863869.16 | I20: PAN Industries | J20: 714.27 | K20: 714270 | L20: 18845.96 | M20: 2352.97 | N20: 8698.96 | O20: 744167.89 | P20: 149599.16 | Q20: 119701.27 | R20: Paid | S20: 863869.16 | T20: 0 | U20: Collected | V20: Social Media | W20: Smallholder Farmer | X20: Osun | Y20: South West | Z20: 0.63 | AA20: =ROUND(H20-O20,2) -> 119701.27 | AB20: =AA20/H20 -> 0.13856412 | AC20: =ROUND(AA20-Q20,2) -> 0 | AD20: 2024 | AE20: 11 | AF20: November | AG20: 2024-11
A21: FZ00020 | B21: 45920 | C21: 45923 | D21: Noiler DOC | E21: 100 | F21: 1003.33 | G21: 1.86 | H21: 98466.81 | I21: Farm Support | J21: 738.3 | K21: 73830 | L21: 2124.59 | M21: 194.49 | N21: 1337.38 | O21: 77486.46 | P21: 24636.81 | Q21: 20980.35 | R21: Paid | S21: 98466.81 | T21: 0 | U21: Collected | V21: WhatsApp | W21: Commercial Farm | X21: Lagos | Y21: South West | Z21: 0.04 | AA21: =ROUND(H21-O21,2) -> 20980.35 | AB21: =AA21/H21 -> 0.21307027 | AC21: =ROUND(AA21-Q21,2) -> 0 | AD21: 2025 | AE21: 9 | AF21: September | AG21: 2025-09
A22: FZ00021 | B22: 45970 | C22: 45982 | D22: Broiler DOC | E22: 1200 | F22: 874.82 | G22: 0.11 | H22: 1048629.2 | I22: AgroPlus NG | J22: 735.28 | K22: 882336 | L22: 12192.83 | M22: 6917.1 | N22: 11134.45 | O22: 912580.38 | P22: 166293.24 | Q22: 136048.86 | R22: Unpaid | S22: 0 | T22: 1048629.2 | U22: Collected | V22: Walk-in | W22: Distributor | X22: Ekiti | Y22: South West | Z22: 2.43 | AA22: =ROUND(H22-O22,2) -> 136048.86 | AB22: =AA22/H22 -> 0.12973972 | AC22: =ROUND(AA22-Q22,2) -> 0 | AD22: 2025 | AE22: 11 | AF22: November | AG22: 2025-11
A23: FZ00022 | B23: 45664 | C23: 45665 | D23: Broiler DOC | E23: 300 | F23: 896.7 | G23: 1.72 | H23: 264383.03 | I23: CHI FARMS | J23: 673.4 | K23: 202020 | L23: 2285.45 | M23: 464.2 | N23: 5447.46 | O23: 210217.11 | P23: 62363.03 | Q23: 54165.92 | R23: Paid | S23: 264383.03 | T23: 0 | U23: Delivered | V23: Reseller | W23: Distributor | X23: Oyo | Y23: South West | Z23: 1.17 | AA23: =ROUND(H23-O23,2) -> 54165.92 | AB23: =AA23/H23 -> 0.20487669 | AC23: =ROUND(AA23-Q23,2) -> 0 | AD23: 2025 | AE23: 1 | AF23: January | AG23: 2025-01
A24: FZ00023 | B24: 45586 | D24: Noiler DOC | E24: 200 | F24: 956.04 | G24: 2.16 | H24: 187077.91 | I24: AgroPlus NG | J24: 767.29 | K24: 153458 | L24: 2593.91 | M24: 679.01 | N24: 9353.25 | O24: 166084.17 | P24: 33619.91 | Q24: 20993.74 | R24: Paid | S24: 187077.91 | T24: 0 | U24: Pending | V24: Walk-in | W24: Agro-dealer | X24: Ekiti | Y24: South West | Z24: 2.48 | AA24: =ROUND(H24-O24,2) -> 20993.74 | AB24: =AA24/H24 -> 0.11221924 | AC24: =ROUND(AA24-Q24,2) -> 0 | AD24: 2024 | AE24: 10 | AF24: October | AG24: 2024-10
A25: FZ00024 | B25: 45875 | C25: 45876 | D25: Broiler DOC | E25: 100 | F25: 866.88 | G25: 1.73 | H25: 85188.3 | I25: Farm Support | J25: 694.6 | K25: 69460 | L25: 1107.83 | M25: 192.58 | N25: 9430.34 | O25: 80190.75 | P25: 15728.3 | Q25: 4997.55 | R25: Paid | S25: 85188.3 | T25: 0 | U25: Collected | V25: Referral | W25: New Customer | X25: Kebbi | Y25: North West | Z25: 0.12 | AA25: =ROUND(H25-O25,2) -> 4997.55 | AB25: =AA25/H25 -> 0.058664746 | AC25: =ROUND(AA25-Q25,2) -> 0 | AD25: 2025 | AE25: 8 | AF25: August | AG25: 2025-08
A26: FZ00025 | B26: 45419 | C26: 45433 | D26: Noiler DOC | E26: 150 | F26: 985.57 | G26: 0.7 | H26: 146800.65 | I26: AgroPlus NG | J26: 757.53 | K26: 113629.5 | L26: 3511.42 | M26: 397.76 | N26: 10539.36 | O26: 128078.04 | P26: 33171.15 | Q26: 18722.61 | R26: Paid | S26: 146800.65 | T26: 0 | U26: Delivered | V26: WhatsApp | W26: Commercial Farm | X26: Gombe | Y26: North East | Z26: 0.96 | AA26: =ROUND(H26-O26,2) -> 18722.61 | AB26: =AA26/H26 -> 0.12753765 | AC26: =ROUND(AA26-Q26,2) -> 0 | AD26: 2024 | AE26: 5 | AF26: May | AG26: 2024-05
A27: FZ00026 | B27: 45879 | C27: 45879 | D27: Broiler DOC | E27: 250 | F27: 893.98 | G27: 0.96 | H27: 221349.45 | I27: AgroPlus NG | J27: 726.94 | K27: 181735 | L27: 2069.76 | M27: 816.06 | N27: 10711.01 | O27: 195331.83 | P27: 39614.45 | Q27: 26017.62 | R27: Paid | S27: 221349.45 | T27: 0 | U27: Delivered | V27: WhatsApp | W27: Commercial Farm | X27: Bayelsa | Y27: South South | Z27: 1.55 | AA27: =ROUND(H27-O27,2) -> 26017.62 | AB27: =AA27/H27 -> 0.11754093 | AC27: =ROUND(AA27-Q27,2) -> 0 | AD27: 2025 | AE27: 8 | AF27: August | AG27: 2025-08
A28: FZ00027 | B28: 45463 | D28: Broiler DOC | E28: 300 | F28: 832.89 | G28: 0.66 | H28: 248217.88 | I28: PAN Industries | J28: 659.94 | K28: 197982 | L28: 4803.96 | M28: 1256.77 | N28: 2373.76 | O28: 206416.49 | P28: 50235.88 | Q28: 41801.39 | R28: Unpaid | S28: 0 | T28: 248217.88 | U28: Pending | V28: Walk-in | W28: Distributor | X28: Sokoto | Y28: North West | Z28: 1.33 | AA28: =ROUND(H28-O28,2) -> 41801.39 | AB28: =AA28/H28 -> 0.16840604 | AC28: =ROUND(AA28-Q28,2) -> 0 | AD28: 2024 | AE28: 6 | AF28: June | AG28: 2024-06
A29: FZ00028 | B29: 45852 | C29: 45859 | D29: Broiler DOC | E29: 50 | F29: 906.03 | G29: 2.2 | H29: 44304.87 | I29: PAN Industries | J29: 671.95 | K29: 33597.5 | L29: 264.61 | M29: 95.03 | N29: 9747.92 | O29: 43705.06 | P29: 10707.37 | Q29: 599.81 | R29: Part-paid | S29: 24041.37 | T29: 20263.5 | U29: Delivered | V29: WhatsApp | W29: New Customer | X29: Edo | Y29: South South | Z29: 1.52 | AA29: =ROUND(H29-O29,2) -> 599.81 | AB29: =AA29/H29 -> 0.013538241 | AC29: =ROUND(AA29-Q29,2) -> 0 | AD29: 2025 | AE29: 7 | AF29: July | AG29: 2025-07
A30: FZ00029 | B30: 45862 | C30: 45868 | D30: Broiler DOC | E30: 300 | F30: 870.02 | G30: 2.08 | H30: 255577.08 | I30: PAN Industries | J30: 656.96 | K30: 197088 | L30: 6174.06 | M30: 1041.36 | N30: 2514.43 | O30: 206817.85 | P30: 58489.08 | Q30: 48759.23 | R30: Paid | S30: 255577.08 | T30: 0 | U30: Delivered | V30: Social Media | W30: Smallholder Farmer | X30: Kogi | Y30: North Central | Z30: 1.69 | AA30: =ROUND(H30-O30,2) -> 48759.23 | AB30: =AA30/H30 -> 0.19078092 | AC30: =ROUND(AA30-Q30,2) -> 0 | AD30: 2025 | AE30: 7 | AF30: July | AG30: 2025-07
A31: FZ00030 | B31: 45753 | D31: Broiler DOC | E31: 200 | F31: 856.96 | G31: 1.82 | H31: 168272.67 | I31: CHI FARMS | J31: 732.87 | K31: 146574 | L31: 3592.05 | M31: 1007.4 | N31: 11173.81 | O31: 162347.26 | P31: 21698.67 | Q31: 5925.41 | R31: Paid | S31: 168272.67 | T31: 0 | U31: Pending | V31: Phone Call | W31: Distributor | X31: Katsina | Y31: North West | Z31: 0.35 | AA31: =ROUND(H31-O31,2) -> 5925.41 | AB31: =AA31/H31 -> 0.035213145 | AC31: =ROUND(AA31-Q31,2) -> 0 | AD31: 2025 | AE31: 4 | AF31: April | AG31: 2025-04
A32: FZ00031 | B32: 45408 | C32: 45421 | D32: Broiler DOC | E32: 200 | F32: 890.13 | G32: 1.24 | H32: 175818.48 | I32: Farm Support | J32: 707.76 | K32: 141552 | L32: 4610.08 | M32: 602.92 | N32: 2749.04 | O32: 149514.04 | P32: 34266.48 | Q32: 26304.44 | R32: Paid | S32: 175818.48 | T32: 0 | U32: Collected | V32: Phone Call | W32: Smallholder Farmer | X32: Edo | Y32: South South | Z32: 1.91 | AA32: =ROUND(H32-O32,2) -> 26304.44 | AB32: =AA32/H32 -> 0.14961135 | AC32: =ROUND(AA32-Q32,2) -> 0 | AD32: 2024 | AE32: 4 | AF32: April | AG32: 2024-04
A33: FZ00032 | B33: 45933 | C33: 45946 | D33: Cockerel DOC | E33: 100 | F33: 787.71 | G33: 0.23 | H33: 78589.83 | I33: AgroPlus NG | J33: 545.51 | K33: 54551 | L33: 1211.32 | M33: 243.64 | N33: 5721.87 | O33: 61727.83 | P33: 24038.83 | Q33: 16862 | R33: Paid | S33: 78589.83 | T33: 0 | U33: Collected | V33: WhatsApp | W33: Smallholder Farmer | X33: Rivers | Y33: South South | Z33: 2.12 | AA33: =ROUND(H33-O33,2) -> 16862 | AB33: =AA33/H33 -> 0.21455702 | AC33: =ROUND(AA33-Q33,2) -> 0 | AD33: 2025 | AE33: 10 | AF33: October | AG33: 2025-10
A34: FZ00033 | B34: 45670 | D34: Noiler DOC | E34: 500 | F34: 968.28 | G34: 0.4 | H34: 0 | I34: Farm Support | J34: 803.36 | K34: 0 | L34: 0 | M34: 0 | N34: 0 | O34: 0 | P34: 0 | Q34: 0 | R34: Part-paid | S34: 0 | T34: 0 | U34: Cancelled | V34: WhatsApp | W34: Smallholder Farmer | X34: Kwara | Y34: North Central | Z34: 1.44 | AA34: =ROUND(H34-O34,2) -> 0 | AB34: =AA34/H34 -> #DIV/0! | AC34: =ROUND(AA34-Q34,2) -> 0 | AD34: 2025 | AE34: 1 | AF34: January | AG34: 2025-01
A35: FZ00034 | B35: 45629 | C35: 45636 | D35: Pullet DOC | E35: 250 | F35: 1429.02 | G35: 2.35 | H35: 348859.51 | I35: Farm Support | J35: 1055.83 | K35: 263957.5 | L35: 5068.41 | M35: 627.41 | N35: 11735.64 | O35: 281388.96 | P35: 84902.01 | Q35: 67470.55 | R35: Paid | S35: 348859.51 | T35: 0 | U35: Delivered | V35: Walk-in | W35: Smallholder Farmer | X35: Imo | Y35: South East | Z35: 2.41 | AA35: =ROUND(H35-O35,2) -> 67470.55 | AB35: =AA35/H35 -> 0.19340321 | AC35: =ROUND(AA35-Q35,2) -> 0 | AD35: 2024 | AE35: 12 | AF35: December | AG35: 2024-12
A36: FZ00035 | B36: 45728 | C36: 45730 | D36: Pullet DOC | E36: 250 | F36: 1388.55 | G36: 0.05 | H36: 346963.93 | I36: CHI FARMS | J36: 974.98 | K36: 243745 | L36: 4852 | M36: 1361.22 | N36: 204.04 | O36: 250162.26 | P36: 103218.93 | Q36: 96801.67 | R36: Part-paid | S36: 91678.99 | T36: 255284.94 | U36: Collected | V36: Reseller | W36: Smallholder Farmer | X36: Anambra | Y36: South East | Z36: 0.7 | AA36: =ROUND(H36-O36,2) -> 96801.67 | AB36: =AA36/H36 -> 0.27899635 | AC36: =ROUND(AA36-Q36,2) -> 0 | AD36: 2025 | AE36: 3 | AF36: March | AG36: 2025-03
A37: FZ00036 | B37: 46004 | C37: 46004 | D37: Turkey Poults | E37: 50 | F37: 2861.17 | G37: 0.04 | H37: 143001.28 | I37: Farm Support | J37: 2444.84 | K37: 122242 | L37: 636.35 | M37: 266.23 | N37: 1489.86 | O37: 124634.44 | P37: 20759.28 | Q37: 18366.84 | R37: Part-paid | S37: 99918.23 | T37: 43083.05 | U37: Delivered | V37: Referral | W37: Commercial Farm | X37: Bauchi | Y37: North East | Z37: 1.09 | AA37: =ROUND(H37-O37,2) -> 18366.84 | AB37: =AA37/H37 -> 0.12843829 | AC37: =ROUND(AA37-Q37,2) -> 0 | AD37: 2025 | AE37: 12 | AF37: December | AG37: 2025-12
A38: FZ00037 | B38: 45642 | C38: 45656 | D38: Noiler DOC | E38: 200 | F38: 988.4 | G38: 2.33 | H38: 193074.06 | I38: AgroPlus NG | J38: 728.18 | K38: 145636 | L38: 4584.32 | M38: 1057.6 | N38: 9535.89 | O38: 160813.81 | P38: 47438.06 | Q38: 32260.25 | R38: Paid | S38: 193074.06 | T38: 0 | U38: Delivered | V38: WhatsApp | W38: Agro-dealer | X38: Oyo | Y38: South West | Z38: 0.9 | AA38: =ROUND(H38-O38,2) -> 32260.25 | AB38: =AA38/H38 -> 0.16708744 | AC38: =ROUND(AA38-Q38,2) -> 0 | AD38: 2024 | AE38: 12 | AF38: December | AG38: 2024-12
A39: FZ00038 | B39: 45641 | C39: 45641 | D39: Broiler DOC | E39: 200 | F39: 874.51 | G39: 0.8 | H39: 173502.78 | I39: CHI FARMS | J39: 696.36 | K39: 139272 | L39: 1103.83 | M39: 442.81 | N39: 4254.52 | O39: 145073.16 | P39: 34230.78 | Q39: 28429.62 | R39: Part-paid | S39: 101562.34 | T39: 71940.44 | U39: Delivered | V39: Social Media | W39: Smallholder Farmer | X39: Lagos | Y39: South West | Z39: 1.27 | AA39: =ROUND(H39-O39,2) -> 28429.62 | AB39: =AA39/H39 -> 0.16385686 | AC39: =ROUND(AA39-Q39,2) -> 0 | AD39: 2024 | AE39: 12 | AF39: December | AG39: 2024-12
A40: FZ00039 | B40: 45328 | D40: Noiler DOC | E40: 1000 | F40: 1004.83 | G40: 5 | H40: 954588.5 | I40: Farm Support | J40: 815.17 | K40: 815170 | L40: 15523.85 | M40: 5576.13 | N40: 3040.11 | O40: 839310.09 | P40: 139418.5 | Q40: 115278.41 | R40: Part-paid | S40: 760073.6 | T40: 194514.9 | U40: Pending | V40: Reseller | W40: Smallholder Farmer | X40: Jigawa | Y40: North West | Z40: 0.28 | AA40: =ROUND(H40-O40,2) -> 115278.41 | AB40: =AA40/H40 -> 0.12076241 | AC40: =ROUND(AA40-Q40,2) -> 0 | AD40: 2024 | AE40: 2 | AF40: February | AG40: 2024-02
A41: FZ00040 | B41: 45725 | C41: 45737 | D41: Pullet DOC | E41: 100 | F41: 1388.46 | G41: 1.2 | H41: 137179.85 | I41: CHI FARMS | J41: 998.79 | K41: 99879 | L41: 1493.95 | M41: 150.39 | N41: 1836.05 | O41: 103359.39 | P41: 37300.85 | Q41: 33820.46 | R41: Paid | S41: 137179.85 | T41: 0 | U41: Delivered | V41: Reseller | W41: Distributor | X41: Ogun | Y41: South West | Z41: 2.22 | AA41: =ROUND(H41-O41,2) -> 33820.46 | AB41: =AA41/H41 -> 0.24654102 | AC41: =ROUND(AA41-Q41,2) -> 0 | AD41: 2025 | AE41: 3 | AF41: March | AG41: 2025-03
A42: FZ00041 | B42: 45906 | C42: 45907 | D42: Broiler DOC | E42: 300 | F42: 854.63 | G42: 2.34 | H42: 250389.5 | I42: Farm Support | J42: 684.8 | K42: 205440 | L42: 5489.88 | M42: 503.12 | N42: 11798.92 | O42: 223231.92 | P42: 44949.5 | Q42: 27157.58 | R42: Paid | S42: 250389.5 | T42: 0 | U42: Delivered | V42: Reseller | W42: Distributor | X42: Ondo | Y42: South West | Z42: 1.28 | AA42: =ROUND(H42-O42,2) -> 27157.58 | AB42: =AA42/H42 -> 0.10846134 | AC42: =ROUND(AA42-Q42,2) -> 0 | AD42: 2025 | AE42: 9 | AF42: September | AG42: 2025-09
A43: FZ00042 | B43: 45780 | D43: Noiler DOC | E43: 200 | F43: 1005.5 | G43: 0.09 | H43: 200919.01 | I43: PAN Industries | J43: 795.89 | K43: 159178 | L43: 2449.58 | M43: 649.69 | N43: 11123.64 | O43: 173400.91 | P43: 41741.01 | Q43: 27518.1 | R43: Paid | S43: 200919.01 | T43: 0 | U43: Pending | V43: Phone Call | W43: Smallholder Farmer | X43: Ekiti | Y43: South West | Z43: 1.26 | AA43: =ROUND(H43-O43,2) -> 27518.1 | AB43: =AA43/H43 -> 0.13696116 | AC43: =ROUND(AA43-Q43,2) -> 0 | AD43: 2025 | AE43: 5 | AF43: May | AG43: 2025-05
A44: FZ00043 | B44: 45898 | C44: 45902 | D44: Noiler DOC | E44: 100 | F44: 1040.98 | G44: 1.57 | H44: 102463.66 | I44: AgroPlus NG | J44: 755.69 | K44: 75569 | L44: 1743.34 | M44: 185.82 | N44: 406.47 | O44: 77904.63 | P44: 26894.66 | Q44: 24559.03 | R44: Paid | S44: 102463.66 | T44: 0 | U44: Collected | V44: WhatsApp | W44: Distributor | X44: Kwara | Y44: North Central | Z44: 1.58 | AA44: =ROUND(H44-O44,2) -> 24559.03 | AB44: =AA44/H44 -> 0.23968527 | AC44: =ROUND(AA44-Q44,2) -> 0 | AD44: 2025 | AE44: 8 | AF44: August | AG44: 2025-08
A45: FZ00044 | B45: 45859 | D45: Pullet DOC | E45: 100 | F45: 1296.17 | G45: 1.24 | H45: 0 | I45: CHI FARMS | J45: 1096.43 | K45: 0 | L45: 0 | M45: 0 | N45: 0 | O45: 0 | P45: 0 | Q45: 0 | R45: Paid | S45: 0 | T45: 0 | U45: Cancelled | V45: Reseller | W45: Smallholder Farmer | X45: Ogun | Y45: South West | Z45: 0.22 | AA45: =ROUND(H45-O45,2) -> 0 | AB45: =AA45/H45 -> #DIV/0! | AC45: =ROUND(AA45-Q45,2) -> 0 | AD45: 2025 | AE45: 7 | AF45: July | AG45: 2025-07
A46: FZ00045 | B46: 45921 | C46: 45935 | D46: Broiler DOC | E46: 200 | F46: 954.25 | G46: 1.92 | H46: 187185.68 | I46: AgroPlus NG | J46: 673.83 | K46: 134766 | L46: 3925.47 | M46: 366.28 | N46: 10015.31 | O46: 149073.06 | P46: 52419.68 | Q46: 38112.62 | R46: Paid | S46: 187185.68 | T46: 0 | U46: Delivered | V46: WhatsApp | W46: Agro-dealer | X46: Osun | Y46: South West | Z46: 1.67 | AA46: =ROUND(H46-O46,2) -> 38112.62 | AB46: =AA46/H46 -> 0.20360863 | AC46: =ROUND(AA46-Q46,2) -> 0 | AD46: 2025 | AE46: 9 | AF46: September | AG46: 2025-09
A47: FZ00046 | B47: 45371 | C47: 45380 | D47: Noiler DOC | E47: 300 | F47: 925.08 | G47: 1.43 | H47: 273555.41 | I47: Farm Support | J47: 824.27 | K47: 247281 | L47: 2874.9 | M47: 1387.87 | N47: 10557.61 | O47: 262101.38 | P47: 26274.41 | Q47: 11454.03 | R47: Paid | S47: 273555.41 | T47: 0 | U47: Delivered | V47: Phone Call | W47: Agro-dealer | X47: Niger | Y47: North Central | Z47: 1.5 | AA47: =ROUND(H47-O47,2) -> 11454.03 | AB47: =AA47/H47 -> 0.041870969 | AC47: =ROUND(AA47-Q47,2) -> 0 | AD47: 2024 | AE47: 3 | AF47: March | AG47: 2024-03
A48: FZ00047 | B48: 45447 | D48: Broiler DOC | E48: 50 | F48: 882.23 | G48: 0.59 | H48: 43851.24 | I48: Farm Support | J48: 739.67 | K48: 36983.5 | L48: 1030.86 | M48: 217.84 | N48: 11336.45 | O48: 49568.65 | P48: 6867.74 | Q48: -5717.41 | R48: Part-paid | S48: 19359.41 | T48: 24491.83 | U48: Pending | V48: Social Media | W48: Distributor | X48: Osun | Y48: South West | Z48: 1.5 | AA48: =ROUND(H48-O48,2) -> -5717.41 | AB48: =AA48/H48 -> -0.13038195 | AC48: =ROUND(AA48-Q48,2) -> 0 | AD48: 2024 | AE48: 6 | AF48: June | AG48: 2024-06
A49: FZ00048 | B49: 45297 | C49: 45308 | D49: Broiler DOC | E49: 750 | F49: 917.88 | G49: 1.99 | H49: 674710.64 | I49: CHI FARMS | J49: 727.98 | K49: 545985 | L49: 6160.4 | M49: 3269.59 | N49: 271.25 | O49: 555686.24 | P49: 128725.64 | Q49: 119024.4 | R49: Paid | S49: 674710.64 | T49: 0 | U49: Delivered | V49: WhatsApp | W49: Smallholder Farmer | X49: Adamawa | Y49: North East | Z49: 0.36 | AA49: =ROUND(H49-O49,2) -> 119024.4 | AB49: =AA49/H49 -> 0.17640807 | AC49: =ROUND(AA49-Q49,2) -> 0 | AD49: 2024 | AE49: 1 | AF49: January | AG49: 2024-01
A50: FZ00049 | B50: 45759 | C50: 45763 | D50: Broiler DOC | E50: 150 | F50: 905.61 | G50: 0.24 | H50: 135515.48 | I50: AgroPlus NG | J50: 692.67 | K50: 103900.5 | L50: 1526.15 | M50: 325.89 | N50: 5526.11 | O50: 111278.65 | P50: 31614.98 | Q50: 24236.83 | R50: Paid | S50: 135515.48 | T50: 0 | U50: Delivered | V50: Reseller | W50: Smallholder Farmer | X50: Gombe | Y50: North East | Z50: 0.27 | AA50: =ROUND(H50-O50,2) -> 24236.83 | AB50: =AA50/H50 -> 0.17884916 | AC50: =ROUND(AA50-Q50,2) -> 0 | AD50: 2025 | AE50: 4 | AF50: April | AG50: 2025-04
A51: FZ00050 | B51: 45546 | C51: 45554 | D51: Pullet DOC | E51: 100 | F51: 1253.81 | G51: 2.41 | H51: 122359.32 | I51: Farm Support | J51: 971.04 | K51: 97104 | L51: 670.26 | M51: 323.85 | N51: 1780.45 | O51: 99878.56 | P51: 25255.32 | Q51: 22480.76 | R51: Paid | S51: 122359.32 | T51: 0 | U51: Delivered | V51: Walk-in | W51: Smallholder Farmer | X51: Lagos | Y51: South West | Z51: 1.15 | AA51: =ROUND(H51-O51,2) -> 22480.76 | AB51: =AA51/H51 -> 0.1837274 | AC51: =ROUND(AA51-Q51,2) -> 0 | AD51: 2024 | AE51: 9 | AF51: September | AG51: 2024-09
A52: FZ00051 | B52: 46001 | C52: 46015 | D52: Pullet DOC | E52: 500 | F52: 1322.3 | G52: 1.6 | H52: 650571.6 | I52: CHI FARMS | J52: 1073.96 | K52: 536980 | L52: 11832.25 | M52: 1374.08 | N52: 3469.73 | O52: 553656.06 | P52: 113591.6 | Q52: 96915.54 | R52: Paid | S52: 650571.6 | T52: 0 | U52: Delivered | V52: Reseller | W52: Distributor | X52: Ondo | Y52: South West | Z52: 1.01 | AA52: =ROUND(H52-O52,2) -> 96915.54 | AB52: =AA52/H52 -> 0.14896983 | AC52: =ROUND(AA52-Q52,2) -> 0 | AD52: 2025 | AE52: 12 | AF52: December | AG52: 2025-12
A53: FZ00052 | B53: 45773 | C53: 45784 | D53: Broiler DOC | E53: 750 | F53: 844.15 | G53: 3.23 | H53: 612662.97 | I53: Farm Support | J53: 723.75 | K53: 542812.5 | L53: 12429.74 | M53: 1437.05 | N53: 5213.58 | O53: 561892.87 | P53: 69850.47 | Q53: 50770.1 | R53: Paid | S53: 612662.97 | T53: 0 | U53: Delivered | V53: Social Media | W53: Agro-dealer | X53: Oyo | Y53: South West | Z53: 1 | AA53: =ROUND(H53-O53,2) -> 50770.1 | AB53: =AA53/H53 -> 0.08286791 | AC53: =ROUND(AA53-Q53,2) -> 0 | AD53: 2025 | AE53: 4 | AF53: April | AG53: 2025-04
A54: FZ00053 | B54: 45978 | C54: 45980 | D54: Broiler DOC | E54: 150 | F54: 873.29 | G54: 0.15 | H54: 130797.01 | I54: CHI FARMS | J54: 663.46 | K54: 99519 | L54: 1104.45 | M54: 797.1 | N54: 4676.73 | O54: 106097.28 | P54: 31278.01 | Q54: 24699.73 | R54: Paid | S54: 130797.01 | T54: 0 | U54: Delivered | V54: WhatsApp | W54: Distributor | X54: Katsina | Y54: North West | Z54: 2.12 | AA54: =ROUND(H54-O54,2) -> 24699.73 | AB54: =AA54/H54 -> 0.18884017 | AC54: =ROUND(AA54-Q54,2) -> 0 | AD54: 2025 | AE54: 11 | AF54: November | AG54: 2025-11
A55: FZ00054 | B55: 45902 | C55: 45911 | D55: Broiler DOC | E55: 1000 | F55: 908.45 | G55: 3.12 | H55: 880106.36 | I55: Farm Support | J55: 712.17 | K55: 712170 | L55: 8734.34 | M55: 4985.81 | N55: 5156.42 | O55: 731046.57 | P55: 167936.36 | Q55: 149059.79 | R55: Unpaid | S55: 0 | T55: 880106.36 | U55: Delivered | V55: Walk-in | W55: Commercial Farm | X55: Akwa Ibom | Y55: South South | Z55: 1.16 | AA55: =ROUND(H55-O55,2) -> 149059.79 | AB55: =AA55/H55 -> 0.16936565 | AC55: =ROUND(AA55-Q55,2) -> 0 | AD55: 2025 | AE55: 9 | AF55: September | AG55: 2025-09
A56: FZ00055 | B56: 45835 | C56: 45843 | D56: Broiler DOC | E56: 150 | F56: 836.99 | G56: 0.69 | H56: 124682.22 | I56: AgroPlus NG | J56: 751.37 | K56: 112705.5 | L56: 2922.84 | M56: 301.43 | N56: 3009.95 | O56: 118939.72 | P56: 11976.72 | Q56: 5742.5 | R56: Part-paid | S56: 41873.6 | T56: 82808.62 | U56: Collected | V56: WhatsApp | W56: New Customer | X56: FCT Abuja | Y56: North Central | Z56: 1.78 | AA56: =ROUND(H56-O56,2) -> 5742.5 | AB56: =AA56/H56 -> 0.046057088 | AC56: =ROUND(AA56-Q56,2) -> 0 | AD56: 2025 | AE56: 6 | AF56: June | AG56: 2025-06
A57: FZ00056 | B57: 45630 | C57: 45644 | D57: Broiler DOC | E57: 200 | F57: 961.87 | G57: 0.55 | H57: 191315.94 | I57: Farm Support | J57: 654.49 | K57: 130898 | L57: 1084.4 | M57: 930.36 | N57: 11121.7 | O57: 144034.46 | P57: 60417.94 | Q57: 47281.48 | R57: Paid | S57: 191315.94 | T57: 0 | U57: Delivered | V57: Walk-in | W57: Commercial Farm | X57: Oyo | Y57: South West | Z57: 2.28 | AA57: =ROUND(H57-O57,2) -> 47281.48 | AB57: =AA57/H57 -> 0.24713822 | AC57: =ROUND(AA57-Q57,2) -> 0 | AD57: 2024 | AE57: 12 | AF57: December | AG57: 2024-12
A58: FZ00057 | B58: 45601 | C58: 45602 | D58: Broiler DOC | E58: 200 | F58: 933.78 | G58: 2.11 | H58: 182815.45 | I58: PAN Industries | J58: 675.61 | K58: 135122 | L58: 4182.04 | M58: 791.31 | N58: 11057.91 | O58: 151153.26 | P58: 47693.45 | Q58: 31662.19 | R58: Unpaid | S58: 0 | T58: 182815.45 | U58: Delivered | V58: Referral | W58: Smallholder Farmer | X58: Rivers | Y58: South South | Z58: 1.2 | AA58: =ROUND(H58-O58,2) -> 31662.19 | AB58: =AA58/H58 -> 0.17319209 | AC58: =ROUND(AA58-Q58,2) -> 0 | AD58: 2024 | AE58: 11 | AF58: November | AG58: 2024-11
A59: FZ00058 | B59: 45339 | C59: 45342 | D59: Broiler DOC | E59: 300 | F59: 819.93 | G59: 1.47 | H59: 242363.11 | I59: PAN Industries | J59: 669.82 | K59: 200946 | L59: 6536.41 | M59: 584.55 | N59: 6538.08 | O59: 214605.04 | P59: 41417.11 | Q59: 27758.07 | R59: Paid | S59: 242363.11 | T59: 0 | U59: Delivered | V59: WhatsApp | W59: Agro-dealer | X59: Jigawa | Y59: North West | Z59: 1.88 | AA59: =ROUND(H59-O59,2) -> 27758.07 | AB59: =AA59/H59 -> 0.11453092 | AC59: =ROUND(AA59-Q59,2) -> 0 | AD59: 2024 | AE59: 2 | AF59: February | AG59: 2024-02
A60: FZ00059 | B60: 45847 | C60: 45861 | D60: Broiler DOC | E60: 1000 | F60: 894.04 | G60: 4.6 | H60: 852914.16 | I60: PAN Industries | J60: 661.35 | K60: 661350 | L60: 19712.04 | M60: 3794.24 | N60: 5233.46 | O60: 690089.74 | P60: 191564.16 | Q60: 162824.42 | R60: Paid | S60: 852914.16 | T60: 0 | U60: Delivered | V60: WhatsApp | W60: Agro-dealer | X60: Bauchi | Y60: North East | Z60: 2.31 | AA60: =ROUND(H60-O60,2) -> 162824.42 | AB60: =AA60/H60 -> 0.19090364 | AC60: =ROUND(AA60-Q60,2) -> 0 | AD60: 2025 | AE60: 7 | AF60: July | AG60: 2025-07
A61: FZ00060 | B61: 45990 | C61: 45999 | D61: Pullet DOC | E61: 300 | F61: 1342.37 | G61: 1.38 | H61: 397153.59 | I61: Farm Support | J61: 1044.28 | K61: 313284 | L61: 1822.22 | M61: 987.17 | N61: 1159.82 | O61: 317253.21 | P61: 83869.59 | Q61: 79900.38 | R61: Part-paid | S61: 247732.82 | T61: 149420.77 | U61: Delivered | V61: Social Media | W61: Agro-dealer | X61: Ebonyi | Y61: South East | Z61: 0.73 | AA61: =ROUND(H61-O61,2) -> 79900.38 | AB61: =AA61/H61 -> 0.20118257 | AC61: =ROUND(AA61-Q61,2) -> 0 | AD61: 2025 | AE61: 11 | AF61: November | AG61: 2025-11
A62: FZ00061 | B62: 45344 | D62: Pullet DOC | E62: 200 | F62: 1325.28 | G62: 0.29 | H62: 0 | I62: AgroPlus NG | J62: 1042.92 | K62: 0 | L62: 0 | M62: 0 | N62: 0 | O62: 0 | P62: 0 | Q62: 0 | R62: Paid | S62: 0 | T62: 0 | U62: Cancelled | V62: Social Media | W62: Smallholder Farmer | X62: Ekiti | Y62: South West | Z62: 1.31 | AA62: =ROUND(H62-O62,2) -> 0 | AB62: =AA62/H62 -> #DIV/0! | AC62: =ROUND(AA62-Q62,2) -> 0 | AD62: 2024 | AE62: 2 | AF62: February | AG62: 2024-02
A63: FZ00062 | B63: 45438 | C63: 45439 | D63: Broiler DOC | E63: 50 | F63: 829.71 | G63: 1.72 | H63: 40771.95 | I63: Farm Support | J63: 659.78 | K63: 32989 | L63: 1179.34 | M63: 176.48 | N63: 11383.84 | O63: 45728.66 | P63: 7782.95 | Q63: -4956.71 | R63: Paid | S63: 40771.95 | T63: 0 | U63: Delivered | V63: WhatsApp | W63: Commercial Farm | X63: Lagos | Y63: South West | Z63: 1.39 | AA63: =ROUND(H63-O63,2) -> -4956.71 | AB63: =AA63/H63 -> -0.12157157 | AC63: =ROUND(AA63-Q63,2) -> 0 | AD63: 2024 | AE63: 5 | AF63: May | AG63: 2024-05
A64: FZ00063 | B64: 45955 | C64: 45957 | D64: Broiler DOC | E64: 1200 | F64: 921.89 | G64: 4.42 | H64: 1057370.9 | I64: Farm Support | J64: 679.61 | K64: 815532 | L64: 26111.74 | M64: 4080.36 | N64: 517.47 | O64: 846241.57 | P64: 241838.95 | Q64: 211129.38 | R64: Paid | S64: 1057370.9 | T64: 0 | U64: Delivered | V64: WhatsApp | W64: Smallholder Farmer | X64: Osun | Y64: South West | Z64: 0.33 | AA64: =ROUND(H64-O64,2) -> 211129.38 | AB64: =AA64/H64 -> 0.1996739 | AC64: =ROUND(AA64-Q64,2) -> 0 | AD64: 2025 | AE64: 10 | AF64: October | AG64: 2025-10
A65: FZ00064 | B65: 45465 | C65: 45470 | D65: Pullet DOC | E65: 750 | F65: 1176.97 | G65: 4.24 | H65: 845299.85 | I65: Farm Support | J65: 1035.38 | K65: 776535 | L65: 13853.18 | M65: 3608.29 | N65: 7246.13 | O65: 801242.6 | P65: 68764.85 | Q65: 44057.25 | R65: Paid | S65: 845299.85 | T65: 0 | U65: Collected | V65: Reseller | W65: Distributor | X65: Abia | Y65: South East | Z65: 1.42 | AA65: =ROUND(H65-O65,2) -> 44057.25 | AB65: =AA65/H65 -> 0.052120262 | AC65: =ROUND(AA65-Q65,2) -> 0 | AD65: 2024 | AE65: 6 | AF65: June | AG65: 2024-06
A66: FZ00065 | B66: 45581 | C66: 45590 | D66: Broiler DOC | E66: 250 | F66: 905.52 | G66: 2.1 | H66: 221626.02 | I66: AgroPlus NG | J66: 689.59 | K66: 172397.5 | L66: 4310.13 | M66: 664.29 | N66: 6337.5 | O66: 183709.42 | P66: 49228.52 | Q66: 37916.6 | R66: Unpaid | S66: 0 | T66: 221626.02 | U66: Delivered | V66: Walk-in | W66: Commercial Farm | X66: Sokoto | Y66: North West | Z66: 1.88 | AA66: =ROUND(H66-O66,2) -> 37916.6 | AB66: =AA66/H66 -> 0.1710837 | AC66: =ROUND(AA66-Q66,2) -> 0 | AD66: 2024 | AE66: 10 | AF66: October | AG66: 2024-10
A67: FZ00066 | B67: 45365 | C67: 45370 | D67: Broiler DOC | E67: 150 | F67: 833.35 | G67: 2.04 | H67: 122452.45 | I67: Farm Support | J67: 731.31 | K67: 109696.5 | L67: 1262.28 | M67: 682.21 | N67: 7350.19 | O67: 118991.18 | P67: 12755.95 | Q67: 3461.27 | R67: Unpaid | S67: 0 | T67: 122452.45 | U67: Delivered | V67: WhatsApp | W67: Commercial Farm | X67: Plateau | Y67: North Central | Z67: 2 | AA67: =ROUND(H67-O67,2) -> 3461.27 | AB67: =AA67/H67 -> 0.028266237 | AC67: =ROUND(AA67-Q67,2) -> 0 | AD67: 2024 | AE67: 3 | AF67: March | AG67: 2024-03
A68: FZ00067 | B68: 45352 | C68: 45358 | D68: Broiler DOC | E68: 150 | F68: 853.25 | G68: 0.77 | H68: 127002 | I68: AgroPlus NG | J68: 654.51 | K68: 98176.5 | L68: 988.93 | M68: 826.67 | N68: 10936.15 | O68: 110928.25 | P68: 28825.5 | Q68: 16073.75 | R68: Paid | S68: 127002 | T68: 0 | U68: Delivered | V68: Reseller | W68: Agro-dealer | X68: Adamawa | Y68: North East | Z68: 1.93 | AA68: =ROUND(H68-O68,2) -> 16073.75 | AB68: =AA68/H68 -> 0.12656297 | AC68: =ROUND(AA68-Q68,2) -> 0 | AD68: 2024 | AE68: 3 | AF68: March | AG68: 2024-03
A69: FZ00068 | B69: 45597 | C69: 45605 | D69: Pullet DOC | E69: 250 | F69: 1360.55 | G69: 0.13 | H69: 339695.32 | I69: CHI FARMS | J69: 997.92 | K69: 249480 | L69: 2058.57 | M69: 1343.72 | N69: 6262.15 | O69: 259144.44 | P69: 90215.32 | Q69: 80550.88 | R69: Paid | S69: 339695.32 | T69: 0 | U69: Collected | V69: Walk-in | W69: New Customer | X69: Ogun | Y69: South West | Z69: 0.33 | AA69: =ROUND(H69-O69,2) -> 80550.88 | AB69: =AA69/H69 -> 0.23712685 | AC69: =ROUND(AA69-Q69,2) -> 0 | AD69: 2024 | AE69: 11 | AF69: November | AG69: 2024-11
A70: FZ00069 | B70: 45800 | C70: 45810 | D70: Pullet DOC | E70: 200 | F70: 1283.36 | G70: 2.17 | H70: 251102.22 | I70: Farm Support | J70: 1109.53 | K70: 221906 | L70: 3929.82 | M70: 733.03 | N70: 3916.57 | O70: 230485.42 | P70: 29196.22 | Q70: 20616.8 | R70: Paid | S70: 251102.22 | T70: 0 | U70: Collected | V70: Walk-in | W70: Commercial Farm | X70: Akwa Ibom | Y70: South South | Z70: 0.56 | AA70: =ROUND(H70-O70,2) -> 20616.8 | AB70: =AA70/H70 -> 0.082105208 | AC70: =ROUND(AA70-Q70,2) -> 0 | AD70: 2025 | AE70: 5 | AF70: May | AG70: 2025-05
A71: FZ00070 | B71: 45810 | C71: 45821 | D71: Noiler DOC | E71: 750 | F71: 1023.27 | G71: 3.62 | H71: 739670.72 | I71: AgroPlus NG | J71: 744.4 | K71: 558300 | L71: 7155.01 | M71: 4124.07 | N71: 8913.88 | O71: 578492.96 | P71: 181370.72 | Q71: 161177.76 | R71: Unpaid | S71: 0 | T71: 739670.72 | U71: Collected | V71: Walk-in | W71: Commercial Farm | X71: Ogun | Y71: South West | Z71: 1.36 | AA71: =ROUND(H71-O71,2) -> 161177.76 | AB71: =AA71/H71 -> 0.21790475 | AC71: =ROUND(AA71-Q71,2) -> 0 | AD71: 2025 | AE71: 6 | AF71: June | AG71: 2025-06
A72: FZ00071 | B72: 45330 | C72: 45330 | D72: Pullet DOC | E72: 500 | F72: 1194 | G72: 2.21 | H72: 583806.3 | I72: CHI FARMS | J72: 1093.76 | K72: 546880 | L72: 8351.61 | M72: 2193.29 | N72: 7711.88 | O72: 565136.78 | P72: 36926.3 | Q72: 18669.52 | R72: Paid | S72: 583806.3 | T72: 0 | U72: Delivered | V72: WhatsApp | W72: Smallholder Farmer | X72: Niger | Y72: North Central | Z72: 1.41 | AA72: =ROUND(H72-O72,2) -> 18669.52 | AB72: =AA72/H72 -> 0.031978963 | AC72: =ROUND(AA72-Q72,2) -> 0 | AD72: 2024 | AE72: 2 | AF72: February | AG72: 2024-02
A73: FZ00072 | B73: 45319 | C73: 45326 | D73: Broiler DOC | E73: 150 | F73: 916.43 | G73: 1.83 | H73: 134948.9 | I73: AgroPlus NG | J73: 702.83 | K73: 105424.5 | L73: 1432.19 | M73: 344.69 | N73: 1941.66 | O73: 109143.04 | P73: 29524.4 | Q73: 25805.86 | R73: Paid | S73: 134948.9 | T73: 0 | U73: Delivered | V73: Walk-in | W73: Smallholder Farmer | X73: Imo | Y73: South East | Z73: 1.54 | AA73: =ROUND(H73-O73,2) -> 25805.86 | AB73: =AA73/H73 -> 0.1912269 | AC73: =ROUND(AA73-Q73,2) -> 0 | AD73: 2024 | AE73: 1 | AF73: January | AG73: 2024-01
A74: FZ00073 | B74: 45876 | C74: 45884 | D74: Noiler DOC | E74: 250 | F74: 967.66 | G74: 1.92 | H74: 237270.23 | I74: Farm Support | J74: 725.21 | K74: 181302.5 | L74: 4004.88 | M74: 389.95 | N74: 1636.43 | O74: 187333.76 | P74: 55967.73 | Q74: 49936.47 | R74: Paid | S74: 237270.23 | T74: 0 | U74: Collected | V74: Phone Call | W74: New Customer | X74: Lagos | Y74: South West | Z74: 1.71 | AA74: =ROUND(H74-O74,2) -> 49936.47 | AB74: =AA74/H74 -> 0.21046243 | AC74: =ROUND(AA74-Q74,2) -> 0 | AD74: 2025 | AE74: 8 | AF74: August | AG74: 2025-08
... A79: FZ00078 | B79: 45545 | C79: 45545 | D79: Broiler DOC | E79: 150 | F79: 939.16 | G79: 0.81 | H79: 139732.92 | I79: AgroPlus NG | J79: 684.27 | K79: 102640.5 | L79: 3310.37 | M79: 508.11 | N79: 5921.3 | O79: 112380.28 | P79: 37092.42 | Q79: 27352.64 | R79: Paid | S79: 139732.92 | T79: 0 | U79: Delivered | V79: WhatsApp | W79: New Customer | X79: Niger | Y79: North Central | Z79: 0.2 | AA79: =ROUND(H79-O79,2) -> 27352.64 | AB79: =AA79/H79 -> 0.19574943 | AC79: =ROUND(AA79-Q79,2) -> 0 | AD79: 2024 | AE79: 9 | AF79: September | AG79: 2024-09
A80: FZ00079 | B80: 45720 | D80: Broiler DOC | E80: 150 | F80: 922.46 | G80: 1.86 | H80: 0 | I80: CHI FARMS | J80: 696.46 | K80: 0 | L80: 0 | M80: 0 | N80: 0 | O80: 0 | P80: 0 | Q80: 0 | R80: Paid | S80: 0 | T80: 0 | U80: Cancelled | V80: Reseller | W80: Agro-dealer | X80: Sokoto | Y80: North West | Z80: 2.16 | AA80: =ROUND(H80-O80,2) -> 0 | AB80: =AA80/H80 -> #DIV/0! | AC80: =ROUND(AA80-Q80,2) -> 0 | AD80: 2025 | AE80: 3 | AF80: March | AG80: 2025-03
A81: FZ00080 | B81: 46012 | D81: Cockerel DOC | E81: 1000 | F81: 762.7 | G81: 2.89 | H81: 740657.97 | I81: Farm Support | J81: 547.77 | K81: 547770 | L81: 7053.38 | M81: 2195.81 | N81: 6489.59 | O81: 563508.78 | P81: 192887.97 | Q81: 177149.19 | R81: Paid | S81: 740657.97 | T81: 0 | U81: Pending | V81: Referral | W81: Smallholder Farmer | X81: Enugu | Y81: South East | Z81: 0.5 | AA81: =ROUND(H81-O81,2) -> 177149.19 | AB81: =AA81/H81 -> 0.23917813 | AC81: =ROUND(AA81-Q81,2) -> 0 | AD81: 2025 | AE81: 12 | AF81: December | AG81: 2025-12
A82: FZ00081 | B82: 45445 | C82: 45451 | D82: Noiler DOC | E82: 100 | F82: 972.56 | G82: 2.1 | H82: 95213.62 | I82: AgroPlus NG | J82: 820.18 | K82: 82018 | L82: 1822.4 | M82: 209.82 | N82: 9694.56 | O82: 93744.78 | P82: 13195.62 | Q82: 1468.84 | R82: Paid | S82: 95213.62 | T82: 0 | U82: Delivered | V82: WhatsApp | W82: Smallholder Farmer | X82: Borno | Y82: North East | Z82: 0.46 | AA82: =ROUND(H82-O82,2) -> 1468.84 | AB82: =AA82/H82 -> 0.015426785 | AC82: =ROUND(AA82-Q82,2) -> 0 | AD82: 2024 | AE82: 6 | AF82: June | AG82: 2024-06
A83: FZ00082 | B83: 45418 | C83: 45425 | D83: Broiler DOC | E83: 750 | F83: 902.34 | G83: 2.64 | H83: 658888.67 | I83: AgroPlus NG | J83: 658.25 | K83: 493687.5 | L83: 5589.68 | M83: 2190.4 | N83: 10682.45 | O83: 512150.03 | P83: 165201.17 | Q83: 146738.64 | R83: Paid | S83: 658888.67 | T83: 0 | U83: Delivered | V83: Phone Call | W83: Commercial Farm | X83: Oyo | Y83: South West | Z83: 1.48 | AA83: =ROUND(H83-O83,2) -> 146738.64 | AB83: =AA83/H83 -> 0.22270627 | AC83: =ROUND(AA83-Q83,2) -> 0 | AD83: 2024 | AE83: 5 | AF83: May | AG83: 2024-05
A84: FZ00083 | B84: 45472 | C84: 45477 | D84: Broiler DOC | E84: 150 | F84: 906.62 | G84: 1.45 | H84: 134021.1 | I84: PAN Industries | J84: 676.95 | K84: 101542.5 | L84: 1930.38 | M84: 377 | N84: 333.45 | O84: 104183.33 | P84: 32478.6 | Q84: 29837.77 | R84: Paid | S84: 134021.1 | T84: 0 | U84: Delivered | V84: Phone Call | W84: Agro-dealer | X84: Bayelsa | Y84: South South | Z84: 1.9 | AA84: =ROUND(H84-O84,2) -> 29837.77 | AB84: =AA84/H84 -> 0.22263487 | AC84: =ROUND(AA84-Q84,2) -> 0 | AD84: 2024 | AE84: 6 | AF84: June | AG84: 2024-06
A85: FZ00084 | B85: 45483 | C85: 45488 | D85: Noiler DOC | E85: 250 | F85: 891.93 | G85: 0.93 | H85: 220908.76 | I85: CHI FARMS | J85: 784.61 | K85: 196152.5 | L85: 3284.53 | M85: 941.77 | N85: 6219.18 | O85: 206597.98 | P85: 24756.26 | Q85: 14310.78 | R85: Paid | S85: 220908.76 | T85: 0 | U85: Collected | V85: Referral | W85: Distributor | X85: Anambra | Y85: South East | Z85: 1.59 | AA85: =ROUND(H85-O85,2) -> 14310.78 | AB85: =AA85/H85 -> 0.064781406 | AC85: =ROUND(AA85-Q85,2) -> 0 | AD85: 2024 | AE85: 7 | AF85: July | AG85: 2024-07
A86: FZ00085 | B86: 45629 | C86: 45642 | D86: Pullet DOC | E86: 200 | F86: 1312.61 | G86: 1.58 | H86: 258374.15 | I86: CHI FARMS | J86: 1021.12 | K86: 204224 | L86: 3632.63 | M86: 1146.05 | N86: 6901.68 | O86: 215904.36 | P86: 54150.15 | Q86: 42469.79 | R86: Paid | S86: 258374.15 | T86: 0 | U86: Delivered | V86: WhatsApp | W86: Commercial Farm | X86: Kaduna | Y86: North West | Z86: 2.04 | AA86: =ROUND(H86-O86,2) -> 42469.79 | AB86: =AA86/H86 -> 0.16437322 | AC86: =ROUND(AA86-Q86,2) -> 0 | AD86: 2024 | AE86: 12 | AF86: December | AG86: 2024-12
A87: FZ00086 | B87: 45629 | C87: 45643 | D87: Broiler DOC | E87: 50 | F87: 972.01 | G87: 0.71 | H87: 48255.44 | I87: Farm Support | J87: 696.05 | K87: 34802.5 | L87: 891.64 | M87: 285.26 | N87: 8058.19 | O87: 44037.59 | P87: 13452.94 | Q87: 4217.85 | R87: Paid | S87: 48255.44 | T87: 0 | U87: Delivered | V87: Referral | W87: Agro-dealer | X87: Taraba | Y87: North East | Z87: 2.03 | AA87: =ROUND(H87-O87,2) -> 4217.85 | AB87: =AA87/H87 -> 0.087406726 | AC87: =ROUND(AA87-Q87,2) -> 0 | AD87: 2024 | AE87: 12 | AF87: December | AG87: 2024-12
A88: FZ00087 | B88: 45280 | C88: 45294 | D88: Pullet DOC | E88: 100 | F88: 1264.03 | G88: 0.33 | H88: 125985.87 | I88: AgroPlus NG | J88: 1105.95 | K88: 110595 | L88: 1978.58 | M88: 443.17 | N88: 4095.59 | O88: 117112.34 | P88: 15390.87 | Q88: 8873.53 | R88: Paid | S88: 125985.87 | T88: 0 | U88: Collected | V88: Social Media | W88: Agro-dealer | X88: Taraba | Y88: North East | Z88: 1.97 | AA88: =ROUND(H88-O88,2) -> 8873.53 | AB88: =AA88/H88 -> 0.07043274 | AC88: =ROUND(AA88-Q88,2) -> 0 | AD88: 2023 | AE88: 12 | AF88: December | AG88: 2023-12
A89: FZ00088 | B89: 45731 | C89: 45731 | D89: Broiler DOC | E89: 100 | F89: 920.67 | G89: 1.76 | H89: 90446.62 | I89: CHI FARMS | J89: 750.52 | K89: 75052 | L89: 1361.36 | M89: 575.17 | N89: 6606.02 | O89: 83594.55 | P89: 15394.62 | Q89: 6852.07 | R89: Paid | S89: 90446.62 | T89: 0 | U89: Delivered | V89: Reseller | W89: Smallholder Farmer | X89: Ebonyi | Y89: South East | Z89: 1.89 | AA89: =ROUND(H89-O89,2) -> 6852.07 | AB89: =AA89/H89 -> 0.075758165 | AC89: =ROUND(AA89-Q89,2) -> 0 | AD89: 2025 | AE89: 3 | AF89: March | AG89: 2025-03
A90: FZ00089 | B90: 45824 | C90: 45834 | D90: Broiler DOC | E90: 750 | F90: 829.07 | G90: 1.3 | H90: 613719.07 | I90: CHI FARMS | J90: 700.38 | K90: 525285 | L90: 17303.03 | M90: 2425.08 | N90: 11242.67 | O90: 556255.78 | P90: 88434.07 | Q90: 57463.29 | R90: Paid | S90: 613719.07 | T90: 0 | U90: Delivered | V90: Walk-in | W90: Smallholder Farmer | X90: Imo | Y90: South East | Z90: 1.58 | AA90: =ROUND(H90-O90,2) -> 57463.29 | AB90: =AA90/H90 -> 0.09363126 | AC90: =ROUND(AA90-Q90,2) -> 0 | AD90: 2025 | AE90: 6 | AF90: June | AG90: 2025-06
A91: FZ00090 | B91: 45891 | C91: 45897 | D91: Broiler DOC | E91: 100 | F91: 914.85 | G91: 2.29 | H91: 89389.99 | I91: CHI FARMS | J91: 688.31 | K91: 68831 | L91: 1838.52 | M91: 474.06 | N91: 10190.27 | O91: 81333.85 | P91: 20558.99 | Q91: 8056.14 | R91: Paid | S91: 89389.99 | T91: 0 | U91: Delivered | V91: Referral | W91: Smallholder Farmer | X91: Niger | Y91: North Central | Z91: 0.2 | AA91: =ROUND(H91-O91,2) -> 8056.14 | AB91: =AA91/H91 -> 0.090123514 | AC91: =ROUND(AA91-Q91,2) -> 0 | AD91: 2025 | AE91: 8 | AF91: August | AG91: 2025-08
A92: FZ00091 | B92: 45853 | C92: 45862 | D92: Cockerel DOC | E92: 100 | F92: 671.07 | G92: 0.58 | H92: 66717.78 | I92: CHI FARMS | J92: 529.3 | K92: 52930 | L92: 1712.72 | M92: 482.9 | N92: 9290.76 | O92: 64416.38 | P92: 13787.78 | Q92: 2301.4 | R92: Part-paid | S92: 28364.57 | T92: 38353.21 | U92: Delivered | V92: WhatsApp | W92: Smallholder Farmer | X92: Imo | Y92: South East | Z92: 0.99 | AA92: =ROUND(H92-O92,2) -> 2301.4 | AB92: =AA92/H92 -> 0.034494553 | AC92: =ROUND(AA92-Q92,2) -> 0 | AD92: 2025 | AE92: 7 | AF92: July | AG92: 2025-07
A93: FZ00092 | B93: 45567 | C93: 45581 | D93: Broiler DOC | E93: 500 | F93: 848.88 | G93: 4.76 | H93: 404236.66 | I93: CHI FARMS | J93: 706.6 | K93: 353300 | L93: 4285.58 | M93: 2663.34 | N93: 8084.24 | O93: 368333.16 | P93: 50936.66 | Q93: 35903.5 | R93: Part-paid | S93: 303148.72 | T93: 101087.94 | U93: Collected | V93: Phone Call | W93: New Customer | X93: Ondo | Y93: South West | Z93: 0.99 | AA93: =ROUND(H93-O93,2) -> 35903.5 | AB93: =AA93/H93 -> 0.088818021 | AC93: =ROUND(AA93-Q93,2) -> 0 | AD93: 2024 | AE93: 10 | AF93: October | AG93: 2024-10
... A95: FZ00094 | B95: 45311 | C95: 45324 | D95: Broiler DOC | E95: 1000 | F95: 852.44 | G95: 2.05 | H95: 834964.98 | I95: CHI FARMS | J95: 670.79 | K95: 670790 | L95: 9853.09 | M95: 3359.08 | N95: 8024.9 | O95: 692027.07 | P95: 164174.98 | Q95: 142937.91 | R95: Paid | S95: 834964.98 | T95: 0 | U95: Delivered | V95: Reseller | W95: Commercial Farm | X95: Oyo | Y95: South West | Z95: 0.18 | AA95: =ROUND(H95-O95,2) -> 142937.91 | AB95: =AA95/H95 -> 0.17119031 | AC95: =ROUND(AA95-Q95,2) -> 0 | AD95: 2024 | AE95: 1 | AF95: January | AG95: 2024-01
A96: FZ00095 | B96: 45962 | D96: Broiler DOC | E96: 300 | F96: 903.76 | G96: 1.63 | H96: 266708.61 | I96: Farm Support | J96: 712.58 | K96: 213774 | L96: 5040.59 | M96: 1131.47 | N96: 10601.83 | O96: 230547.89 | P96: 52934.61 | Q96: 36160.72 | R96: Paid | S96: 266708.61 | T96: 0 | U96: Pending | V96: WhatsApp | W96: Commercial Farm | X96: Anambra | Y96: South East | Z96: 1.03 | AA96: =ROUND(H96-O96,2) -> 36160.72 | AB96: =AA96/H96 -> 0.13558137 | AC96: =ROUND(AA96-Q96,2) -> 0 | AD96: 2025 | AE96: 11 | AF96: November | AG96: 2025-11
A97: FZ00096 | B97: 45615 | C97: 45620 | D97: Pullet DOC | E97: 200 | F97: 1345.78 | G97: 1.91 | H97: 264015.12 | I97: CHI FARMS | J97: 1054.36 | K97: 210872 | L97: 2151.59 | M97: 455.02 | N97: 2491.88 | O97: 215970.49 | P97: 53143.12 | Q97: 48044.63 | R97: Paid | S97: 264015.12 | T97: 0 | U97: Collected | V97: WhatsApp | W97: Smallholder Farmer | X97: Kwara | Y97: North Central | Z97: 0.89 | AA97: =ROUND(H97-O97,2) -> 48044.63 | AB97: =AA97/H97 -> 0.18197681 | AC97: =ROUND(AA97-Q97,2) -> 0 | AD97: 2024 | AE97: 11 | AF97: November | AG97: 2024-11
A98: FZ00097 | B98: 45695 | C98: 45708 | D98: Pullet DOC | E98: 500 | F98: 1348.84 | G98: 3.43 | H98: 651287.39 | I98: Farm Support | J98: 977.88 | K98: 488940 | L98: 8462.86 | M98: 1855.53 | N98: 6253.83 | O98: 505512.22 | P98: 162347.39 | Q98: 145775.17 | R98: Unpaid | S98: 0 | T98: 651287.39 | U98: Delivered | V98: Social Media | W98: Smallholder Farmer | X98: Ekiti | Y98: South West | Z98: 1.99 | AA98: =ROUND(H98-O98,2) -> 145775.17 | AB98: =AA98/H98 -> 0.22382618 | AC98: =ROUND(AA98-Q98,2) -> 0 | AD98: 2025 | AE98: 2 | AF98: February | AG98: 2025-02
A99: FZ00098 | B99: 45654 | C99: 45657 | D99: Broiler DOC | E99: 200 | F99: 865.75 | G99: 0.56 | H99: 172180.36 | I99: AgroPlus NG | J99: 649.66 | K99: 129932 | L99: 2714.01 | M99: 385.3 | N99: 9949.89 | O99: 142981.2 | P99: 42248.36 | Q99: 29199.16 | R99: Paid | S99: 172180.36 | T99: 0 | U99: Delivered | V99: WhatsApp | W99: Agro-dealer | X99: Lagos | Y99: South West | Z99: 1.2 | AA99: =ROUND(H99-O99,2) -> 29199.16 | AB99: =AA99/H99 -> 0.16958473 | AC99: =ROUND(AA99-Q99,2) -> 0 | AD99: 2024 | AE99: 12 | AF99: December | AG99: 2024-12
A100: FZ00099 | B100: 45523 | D100: Cockerel DOC | E100: 150 | F100: 707.39 | G100: 0.79 | H100: 105270.24 | I100: CHI FARMS | J100: 526.99 | K100: 79048.5 | L100: 1859.56 | M100: 797.41 | N100: 8870.28 | O100: 90575.75 | P100: 26221.74 | Q100: 14694.49 | R100: Paid | S100: 105270.24 | T100: 0 | U100: Pending | V100: Reseller | W100: Commercial Farm | X100: Ebonyi | Y100: South East | Z100: 2.27 | AA100: =ROUND(H100-O100,2) -> 14694.49 | AB100: =AA100/H100 -> 0.13958826 | AC100: =ROUND(AA100-Q100,2) -> 0 | AD100: 2024 | AE100: 8 | AF100: August | AG100: 2024-08
A101: FZ00100 | B101: 46011 | C101: 46014 | D101: Broiler DOC | E101: 750 | F101: 891.62 | G101: 0.64 | H101: 664435.22 | I101: PAN Industries | J101: 671.59 | K101: 503692.5 | L101: 16464.74 | M101: 4497.19 | N101: 6655.28 | O101: 531309.71 | P101: 160742.72 | Q101: 133125.51 | R101: Part-paid | S101: 206197.08 | T101: 458238.14 | U101: Delivered | V101: Phone Call | W101: Agro-dealer | X101: Sokoto | Y101: North West | Z101: 1.69 | AA101: =ROUND(H101-O101,2) -> 133125.51 | AB101: =AA101/H101 -> 0.2003589 | AC101: =ROUND(AA101-Q101,2) -> 0 | AD101: 2025 | AE101: 12 | AF101: December | AG101: 2025-12
A102: FZ00101 | B102: 45600 | C102: 45608 | D102: Cockerel DOC | E102: 150 | F102: 732.23 | G102: 1.64 | H102: 108033.21 | I102: AgroPlus NG | J102: 530.84 | K102: 79626 | L102: 2910.24 | M102: 536.23 | N102: 5889.96 | O102: 88962.43 | P102: 28407.21 | Q102: 19070.78 | R102: Paid | S102: 108033.21 | T102: 0 | U102: Delivered | V102: Reseller | W102: Agro-dealer | X102: Ondo | Y102: South West | Z102: 0.32 | AA102: =ROUND(H102-O102,2) -> 19070.78 | AB102: =AA102/H102 -> 0.17652701 | AC102: =ROUND(AA102-Q102,2) -> 0 | AD102: 2024 | AE102: 11 | AF102: November | AG102: 2024-11
A103: FZ00102 | B103: 45797 | C103: 45801 | D103: Broiler DOC | E103: 200 | F103: 834.39 | G103: 1.2 | H103: 164875.46 | I103: AgroPlus NG | J103: 696.6 | K103: 139320 | L103: 1938.66 | M103: 1064.52 | N103: 9057.88 | O103: 151381.06 | P103: 25555.46 | Q103: 13494.4 | R103: Paid | S103: 164875.46 | T103: 0 | U103: Delivered | V103: WhatsApp | W103: Smallholder Farmer | X103: FCT Abuja | Y103: North Central | Z103: 0 | AA103: =ROUND(H103-O103,2) -> 13494.4 | AB103: =AA103/H103 -> 0.081846019 | AC103: =ROUND(AA103-Q103,2) -> 0 | AD103: 2025 | AE103: 5 | AF103: May | AG103: 2025-05
A104: FZ00103 | B104: 45589 | C104: 45601 | D104: Pullet DOC | E104: 1000 | F104: 1280.13 | G104: 4.81 | H104: 1218555.8 | I104: AgroPlus NG | J104: 986.39 | K104: 986390 | L104: 18815.71 | M104: 3530.23 | N104: 10496.16 | O104: 1019232.1 | P104: 232165.75 | Q104: 199323.65 | R104: Paid | S104: 1218555.8 | T104: 0 | U104: Collected | V104: WhatsApp | W104: Commercial Farm | X104: Imo | Y104: South East | Z104: 1.26 | AA104: =ROUND(H104-O104,2) -> 199323.65 | AB104: =AA104/H104 -> 0.16357368 | AC104: =ROUND(AA104-Q104,2) -> 0 | AD104: 2024 | AE104: 10 | AF104: October | AG104: 2024-10
A105: FZ00104 | B105: 45405 | C105: 45405 | D105: Noiler DOC | E105: 750 | F105: 982.28 | G105: 2.71 | H105: 716745.16 | I105: PAN Industries | J105: 742.75 | K105: 557062.5 | L105: 12974.54 | M105: 3680.46 | N105: 1081.5 | O105: 574799 | P105: 159682.66 | Q105: 141946.16 | R105: Part-paid | S105: 387857.66 | T105: 328887.5 | U105: Delivered | V105: Referral | W105: New Customer | X105: Kaduna | Y105: North West | Z105: 1.79 | AA105: =ROUND(H105-O105,2) -> 141946.16 | AB105: =AA105/H105 -> 0.19804272 | AC105: =ROUND(AA105-Q105,2) -> 0 | AD105: 2024 | AE105: 4 | AF105: April | AG105: 2024-04
...

Sheet Pivot Table
G1: Product_Type | H1: (All) | J1: Product_Type | K1: (All) | Y1: Product_Type | Z1: (All)
Y2: State | Z2: (All) | AO2: Product_Type | AP2: (All)
A3: Row Labels | B3: Sum of Unit_Selling_Price_NGN | G3: Row Labels | H3: Count of Quantity_Ordered | J3: Average of Unit_Selling_Price_NGN | K3: Column Labels | P3: Sum of Order_Year | Q3: Column Labels
A4: Abia | B4: 4110.44 | G4: Abia | H4: 41 | J4: Row Labels | K4: Supplier A | L4: Supplier B | M4: Supplier C | N4: Supplier D | O4: Grand Total | P4: Row Labels | Q4: Broiler DOC | R4: Cockerel DOC | S4: Noiler DOC | T4: Pullet DOC | U4: Turkey Poults | V4: Grand Total | Y4: Row Labels | Z4: Sum of Quantity_Ordered | AA4: Sum of Revenue_NGN | AB4: Sum of Net_Profit_NGN | AC4: Count of Order_ID | AE4: Count of Delivery_Status | AF4: Column Labels | AO4: Average of Quantity_Ordered | AP4: Column Labels | AW4: Sum of Quantity_Ordered | AX4: Column Labels
A5: Adamawa | B5: 1033.12 | G5: Adamawa | H5: 22 | J5: North Central | K5: 1051.0112 | L5: 1059.9676 | M5: 1088.1403 | N5: 969.26091 | O5: 1052.519 | P5: Abia | Q5: 38460 | S5: 18219 | T5: 22269 | U5: 4050 | V5: 82998 | Y5: Phone Call | Z5: 90300 | AA5: 88908967 | AB5: 14544651 | AC5: 246 | AE5: Row Labels | AF5: Broiler DOC | AG5: Cockerel DOC | AH5: Noiler DOC | AI5: Pullet DOC | AJ5: Turkey Poults | AK5: Grand Total | AO5: Row Labels | AP5: 2023 | AQ5: 2024 | AR5: 2025 | AS5: Grand Total | AW5: Row Labels | AX5: Broiler DOC | AY5: Cockerel DOC | AZ5: Noiler DOC | BA5: Pullet DOC | BB5: Turkey Poults | BC5: Grand Total
A6: Akwa Ibom | B6: 2943.95 | G6: Akwa Ibom | H6: 38 | J6: North East | K6: 1059.7776 | L6: 959.21533 | M6: 1087.6741 | N6: 1213.2288 | O6: 1062.4521 | P6: Adamawa | Q6: 26316 | S6: 8097 | T6: 8097 | U6: 2024 | V6: 44534 | Y6: Referral | Z6: 64700 | AA6: 65368251 | AB6: 10159358 | AC6: 197 | AE6: Abia | AF6: 19 | AH6: 9 | AI6: 11 | AJ6: 2 | AK6: 41 | AO6: North Central | AP6: 750 | AQ6: 335.18519 | AR6: 351.83486 | AS6: 347.26027 | AW6: Abia | AX6: 6100 | AZ6: 3700 | BA6: 4250 | BB6: 1000 | BC6: 15050
A7: Anambra | B7: 891.93 | G7: Anambra | H7: 46 | J7: North West | K7: 1230.0003 | L7: 1057.9494 | M7: 972.77714 | N7: 1083.8219 | O7: 1108.0228 | P7: Akwa Ibom | Q7: 44543 | R7: 4049 | S7: 10124 | T7: 12148 | U7: 6074 | V7: 76938 | Y7: Reseller | Z7: 79900 | AA7: 80708958 | AB7: 11901014 | AC7: 222 | AE7: Adamawa | AF7: 13 | AH7: 4 | AI7: 4 | AJ7: 1 | AK7: 22 | AO7: North East | AP7: 100 | AQ7: 329.23077 | AR7: 365.07937 | AS7: 344.96124 | AW7: Adamawa | AX7: 4250 | AZ7: 1450 | BA7: 950 | BB7: 250 | BC7: 6900
A8: Bauchi | B8: 937.99 | G8: Bauchi | H8: 25 | J8: South East | K8: 1052.624 | L8: 988.85304 | M8: 1149.079 | N8: 1031.0628 | O8: 1053.6482 | P8: Anambra | Q8: 42516 | R8: 18221 | S8: 2024 | T8: 28341 | U8: 2024 | V8: 93126 | Y8: Social Media | Z8: 60850 | AA8: 59837675 | AB8: 9206774.1 | AC8: 190 | AE8: Akwa Ibom | AF8: 22 | AG8: 2 | AH8: 5 | AI8: 6 | AJ8: 3 | AK8: 38 | AO8: North West | AP8: 1000 | AQ8: 293.29897 | AR8: 368.30357 | AS8: 336.66667 | AW8: Akwa Ibom | AX8: 8550 | AY8: 350 | AZ8: 2500 | BA8: 1200 | BB8: 1300 | BC8: 13900
A9: Bayelsa | B9: 1010.36 | G9: Bayelsa | H9: 34 | J9: South South | K9: 1056.3318 | L9: 1060.2566 | M9: 1049.8051 | N9: 1084.6975 | O9: 1058.9101 | P9: Bauchi | Q9: 34418 | R9: 2024 | S9: 10123 | T9: 2024 | U9: 2025 | V9: 50614 | Y9: Walk-in | Z9: 52450 | AA9: 52085813 | AB9: 8653235.9 | AC9: 160 | AE9: Anambra | AF9: 21 | AG9: 9 | AH9: 1 | AI9: 14 | AJ9: 1 | AK9: 46 | AO9: South East | AP9: 275 | AQ9: 340.7563 | AR9: 347.0297 | AS9: 343.01802 | AW9: Anambra | AX9: 7150 | AY9: 1900 | AZ9: 250 | BA9: 5350 | BB9: 150 | BC9: 14800
A10: Benue | B10: 994.65 | G10: Benue | H10: 25 | J10: South West | K10: 1028.3791 | L10: 990.97049 | M10: 1052.1132 | N10: 1038.2829 | O10: 1022.5918 | P10: Bayelsa | Q10: 32394 | R10: 10122 | S10: 14174 | T10: 10123 | U10: 2025 | V10: 68838 | Y10: WhatsApp | Z10: 160450 | AA10: 1.6178002e+08 | AB10: 25044933 | AC10: 485 | AE10: Bauchi | AF10: 17 | AG10: 1 | AH10: 5 | AI10: 1 | AJ10: 1 | AK10: 25 | AO10: South South | AP10: 160 | AQ10: 295.34884 | AR10: 347.24771 | AS10: 320.25 | AW10: Bauchi | AX10: 6700 | AY10: 200 | AZ10: 2500 | BA10: 300 | BB10: 50 | BC10: 9750
A11: Delta | B11: 3932.55 | G11: Borno | H11: 18 | J11: Grand Total | K11: 1070.0709 | L11: 1018.7286 | M11: 1064.9925 | N11: 1058.6257 | O11: 1051.7883 | P11: Benue | Q11: 24294 | R11: 2024 | S11: 6074 | T11: 16197 | U11: 2025 | V11: 50614 | Y11: Grand Total | Z11: 508650 | AA11: 5.0868969e+08 | AB11: 79509966 | AC11: 1500 | AE11: Bayelsa | AF11: 16 | AG11: 5 | AH11: 7 | AI11: 5 | AJ11: 1 | AK11: 34 | AO11: South West | AP11: 1000 | AQ11: 351.27273 | AR11: 326.22951 | AS11: 340.76923 | AW11: Bayelsa | AX11: 6800 | AY11: 2000 | AZ11: 3400 | BA11: 1350 | BB11: 750 | BC11: 14300
A12: Ebonyi | B12: 2001.9 | G12: Cross River | H12: 38 | P12: Borno | Q12: 16197 | R12: 6073 | S12: 8098 | T12: 4050 | U12: 2025 | V12: 36443 | AE12: Benue | AF12: 12 | AG12: 1 | AH12: 3 | AI12: 8 | AJ12: 1 | AK12: 25 | AO12: Grand Total | AP12: 412.5 | AQ12: 331.46667 | AR12: 345.66396 | AS12: 339.1 | AW12: Benue | AX12: 4300 | AY12: 300 | AZ12: 1450 | BA12: 2500 | BB12: 750 | BC12: 9300
A13: Edo | B13: 1914.22 | G13: Delta | H13: 31 | P13: Cross River | Q13: 44541 | R13: 2024 | S13: 10122 | T13: 18219 | U13: 2025 | V13: 76931 | AE13: Borno | AF13: 8 | AG13: 3 | AH13: 4 | AI13: 2 | AJ13: 1 | AK13: 18 | AW13: Borno | AX13: 1850 | AY13: 800 | AZ13: 2100 | BA13: 450 | BB13: 750 | BC13: 5950
A14: Ekiti | B14: 2887.98 | G14: Ebonyi | H14: 57 | P14: Delta | Q14: 28342 | R14: 8098 | S14: 16194 | T14: 6074 | U14: 4049 | V14: 62757 | AE14: Cross River | AF14: 22 | AG14: 1 | AH14: 5 | AI14: 9 | AJ14: 1 | AK14: 38 | AW14: Cross River | AX14: 7150 | AY14: 50 | AZ14: 1450 | BA14: 2300 | BB14: 50 | BC14: 11000
A15: Enugu | B15: 1004.88 | G15: Edo | H15: 30 | P15: Ebonyi | Q15: 56685 | R15: 10122 | S15: 14172 | T15: 28342 | U15: 6074 | V15: 115395 | AE15: Delta | AF15: 14 | AG15: 4 | AH15: 8 | AI15: 3 | AJ15: 2 | AK15: 31 | AW15: Delta | AX15: 4800 | AY15: 450 | AZ15: 1200 | BA15: 1150 | BB15: 300 | BC15: 7900
A16: FCT Abuja | B16: 1922.87 | G16: Ekiti | H16: 92 | P16: Edo | Q16: 30366 | R16: 4049 | S16: 12145 | T16: 10122 | U16: 4049 | V16: 60731 | AE16: Ebonyi | AF16: 28 | AG16: 5 | AH16: 7 | AI16: 14 | AJ16: 3 | AK16: 57 | AW16: Ebonyi | AX16: 9050 | AY16: 1100 | AZ16: 1850 | BA16: 4200 | BB16: 700 | BC16: 16900
A17: Imo | B17: 2842.34 | G17: Enugu | H17: 43 | P17: Ekiti | Q17: 89077 | R17: 8097 | S17: 32392 | T17: 54660 | U17: 2024 | V17: 186250 | AE17: Edo | AF17: 15 | AG17: 2 | AH17: 6 | AI17: 5 | AJ17: 2 | AK17: 30 | AW17: Edo | AX17: 3950 | AY17: 200 | AZ17: 1150 | BA17: 1850 | BB17: 150 | BC17: 7300
A18: Jigawa | B18: 1864.86 | G18: FCT Abuja | H18: 35 | P18: Enugu | Q18: 42515 | R18: 10122 | S18: 8097 | T18: 24295 | U18: 2024 | V18: 87053 | AE18: Ekiti | AF18: 44 | AG18: 4 | AH18: 16 | AI18: 27 | AJ18: 1 | AK18: 92 | AW18: Ekiti | AX18: 16350 | AY18: 1700 | AZ18: 3800 | BA18: 9700 | BB18: 750 | BC18: 32300
A19: Kaduna | B19: 1007.93 | G19: Gombe | H19: 17 | P19: FCT Abuja | Q19: 32390 | R19: 4049 | S19: 10120 | T19: 22272 | U19: 2024 | V19: 70855 | AE19: Enugu | AF19: 21 | AG19: 5 | AH19: 4 | AI19: 12 | AJ19: 1 | AK19: 43 | AW19: Enugu | AX19: 8900 | AY19: 2100 | AZ19: 1700 | BA19: 3150 | BB19: 50 | BC19: 15900
A20: Katsina | B20: 1980.16 | G20: Imo | H20: 35 | P20: Gombe | Q20: 18221 | R20: 2024 | S20: 4049 | T20: 10121 | V20: 34415 | AE20: FCT Abuja | AF20: 16 | AG20: 2 | AH20: 5 | AI20: 11 | AJ20: 1 | AK20: 35 | AW20: FCT Abuja | AX20: 4800 | AY20: 1700 | AZ20: 1200 | BA20: 3850 | BB20: 50 | BC20: 11600
A21: Kwara | B21: 2983.49 | G21: Jigawa | H21: 37 | P21: Imo | Q21: 38463 | R21: 8098 | S21: 12147 | T21: 12147 | V21: 70855 | AE21: Gombe | AF21: 9 | AG21: 1 | AH21: 2 | AI21: 5 | AK21: 17 | AW21: Gombe | AX21: 1800 | AY21: 250 | AZ21: 1150 | BA21: 2650 | BC21: 5850
A22: Lagos | B22: 5762.38 | G22: Kaduna | H22: 35 | P22: Jigawa | Q22: 36439 | R22: 2025 | S22: 12145 | T22: 16195 | U22: 8099 | V22: 74903 | AE22: Imo | AF22: 19 | AG22: 4 | AH22: 6 | AI22: 6 | AK22: 35 | AW22: Imo | AX22: 8050 | AY22: 1650 | AZ22: 1250 | BA22: 2550 | BC22: 13500
A23: Nasarawa | B23: 1976.91 | G23: Kano | H23: 29 | P23: Kaduna | Q23: 28343 | R23: 10120 | S23: 10124 | T23: 22270 | V23: 70857 | AE23: Jigawa | AF23: 18 | AG23: 1 | AH23: 6 | AI23: 8 | AJ23: 4 | AK23: 37 | AW23: Jigawa | AX23: 6100 | AY23: 500 | AZ23: 3300 | BA23: 2250 | BB23: 1350 | BC23: 13500
A24: Ogun | B24: 4885.01 | G24: Katsina | H24: 31 | P24: Kano | Q24: 28346 | R24: 2025 | S24: 6075 | T24: 18223 | U24: 4050 | V24: 58719 | AE24: Kaduna | AF24: 14 | AG24: 5 | AH24: 5 | AI24: 11 | AK24: 35 | AW24: Kaduna | AX24: 4800 | AY24: 900 | AZ24: 1750 | BA24: 3450 | BC24: 10900
A25: Ondo | B25: 1941.21 | G25: Kebbi | H25: 23 | P25: Katsina | Q25: 28344 | R25: 4049 | S25: 10121 | T25: 16198 | U25: 4050 | V25: 62762 | AE25: Kano | AF25: 14 | AG25: 1 | AH25: 3 | AI25: 9 | AJ25: 2 | AK25: 29 | AW25: Kano | AX25: 6050 | AY25: 150 | AZ25: 450 | BA25: 3100 | BB25: 300 | BC25: 10050
A26: Osun | B26: 966.7 | G26: Kogi | H26: 37 | P26: Kebbi | Q26: 30365 | R26: 4049 | T26: 8099 | U26: 4050 | V26: 46563 | AE26: Katsina | AF26: 14 | AG26: 2 | AH26: 5 | AI26: 8 | AJ26: 2 | AK26: 31 | AW26: Katsina | AX26: 5200 | AY26: 250 | AZ26: 1950 | BA26: 3100 | BB26: 100 | BC26: 10600
A27: Oyo | B27: 5793.1 | G27: Kwara | H27: 33 | P27: Kogi | Q27: 42510 | S27: 6073 | T27: 26320 | V27: 74903 | AE27: Kebbi | AF27: 15 | AG27: 2 | AI27: 4 | AJ27: 2 | AK27: 23 | AW27: Kebbi | AX27: 5050 | AY27: 800 | BA27: 1350 | BB27: 1250 | BC27: 8450
A28: Plateau | B28: 4056.56 | G28: Lagos | H28: 88 | P28: Kwara | Q28: 30367 | R28: 4050 | S28: 18222 | T28: 12148 | U28: 2024 | V28: 66811 | AE28: Kogi | AF28: 21 | AH28: 3 | AI28: 13 | AK28: 37 | AW28: Kogi | AX28: 7850 | AZ28: 1250 | BA28: 2150 | BC28: 11250
A29: Rivers | B29: 1962.14 | G29: Nasarawa | H29: 28 | P29: Lagos | Q29: 103245 | R29: 16196 | S29: 28346 | T29: 28344 | U29: 2025 | V29: 178156 | AE29: Kwara | AF29: 15 | AG29: 2 | AH29: 9 | AI29: 6 | AJ29: 1 | AK29: 33 | AW29: Kwara | AX29: 5100 | AY29: 850 | AZ29: 3050 | BA29: 1400 | BB29: 150 | BC29: 10550
A30: Taraba | B30: 937.78 | G30: Niger | H30: 27 | P30: Nasarawa | Q30: 30369 | R30: 2024 | S30: 8099 | T30: 14172 | U30: 2024 | V30: 56688 | AE30: Lagos | AF30: 51 | AG30: 8 | AH30: 14 | AI30: 14 | AJ30: 1 | AK30: 88 | AW30: Lagos | AX30: 18550 | AY30: 2400 | AZ30: 3400 | BA30: 3350 | BB30: 150 | BC30: 27850
A31: Grand Total | B31: 64547.41 | G31: Ogun | H31: 90 | P31: Niger | Q31: 30364 | R31: 4049 | S31: 8097 | T31: 10124 | U31: 2025 | V31: 54659 | AE31: Nasarawa | AF31: 15 | AG31: 1 | AH31: 4 | AI31: 7 | AJ31: 1 | AK31: 28 | AW31: Nasarawa | AX31: 4800 | AY31: 250 | AZ31: 2250 | BA31: 3150 | BB31: 750 | BC31: 11200
G32: Ondo | H32: 72 | P32: Ogun | Q32: 95149 | R32: 10122 | S32: 30368 | T32: 44537 | U32: 2024 | V32: 182200 | AE32: Niger | AF32: 15 | AG32: 2 | AH32: 4 | AI32: 5 | AJ32: 1 | AK32: 27 | AW32: Niger | AX32: 5500 | AY32: 950 | AZ32: 1650 | BA32: 1500 | BB32: 250 | BC32: 9850
G33: Osun | H33: 75 | P33: Ondo | Q33: 64784 | R33: 20244 | S33: 14171 | T33: 42514 | U33: 4049 | V33: 145762 | AE33: Ogun | AF33: 47 | AG33: 5 | AH33: 15 | AI33: 22 | AJ33: 1 | AK33: 90 | AW33: Ogun | AX33: 16250 | AY33: 1400 | AZ33: 6200 | BA33: 6750 | BB33: 750 | BC33: 31350
G34: Oyo | H34: 103 | P34: Osun | Q34: 93127 | R34: 10123 | S34: 6074 | T34: 32392 | U34: 10123 | V34: 151839 | AE34: Ondo | AF34: 32 | AG34: 10 | AH34: 7 | AI34: 21 | AJ34: 2 | AK34: 72 | AW34: Ondo | AX34: 8550 | AY34: 3850 | AZ34: 1600 | BA34: 7600 | BB34: 150 | BC34: 21750
G35: Plateau | H35: 34 | P35: Oyo | Q35: 119442 | R35: 20243 | S35: 30368 | T35: 32391 | U35: 6072 | V35: 208516 | AE35: Osun | AF35: 46 | AG35: 5 | AH35: 3 | AI35: 16 | AJ35: 5 | AK35: 75 | AW35: Osun | AX35: 17000 | AY35: 1250 | AZ35: 400 | BA35: 5150 | BB35: 3000 | BC35: 26800
G36: Rivers | H36: 29 | P36: Plateau | Q36: 28342 | R36: 8097 | S36: 16197 | T36: 14172 | U36: 2025 | V36: 68833 | AE36: Oyo | AF36: 59 | AG36: 10 | AH36: 15 | AI36: 16 | AJ36: 3 | AK36: 103 | AW36: Oyo | AX36: 21600 | AY36: 3500 | AZ36: 5350 | BA36: 6000 | BB36: 700 | BC36: 37150
G37: Sokoto | H37: 29 | P37: Rivers | Q37: 28342 | R37: 6075 | S37: 14171 | T37: 8096 | U37: 2025 | V37: 58709 | AE37: Plateau | AF37: 14 | AG37: 4 | AH37: 8 | AI37: 7 | AJ37: 1 | AK37: 34 | AW37: Plateau | AX37: 5300 | AY37: 1900 | AZ37: 2200 | BA37: 2800 | BB37: 100 | BC37: 12300
G38: Taraba | H38: 23 | P38: Sokoto | Q38: 38464 | R38: 4049 | S38: 6074 | T38: 10122 | V38: 58709 | AE38: Rivers | AF38: 14 | AG38: 3 | AH38: 7 | AI38: 4 | AJ38: 1 | AK38: 29 | AW38: Rivers | AX38: 3950 | AY38: 550 | AZ38: 3000 | BA38: 1650 | BB38: 500 | BC38: 9650
G39: Yobe | H39: 24 | P39: Taraba | Q39: 26319 | R39: 2024 | S39: 2024 | T39: 12146 | U39: 4049 | V39: 46562 | AE39: Sokoto | AF39: 19 | AG39: 2 | AH39: 3 | AI39: 5 | AK39: 29 | AW39: Sokoto | AX39: 5100 | AY39: 1250 | AZ39: 500 | BA39: 1000 | BC39: 7850
G40: Zamfara | H40: 26 | P40: Yobe | Q40: 26318 | R40: 4050 | S40: 6074 | T40: 10123 | U40: 2025 | V40: 48590 | AE40: Taraba | AF40: 13 | AG40: 1 | AH40: 1 | AI40: 6 | AJ40: 2 | AK40: 23 | AW40: Taraba | AX40: 3250 | AY40: 150 | AZ40: 1000 | BA40: 2150 | BB40: 800 | BC40: 7350
G41: Grand Total | H41: 1500 | P41: Zamfara | Q41: 26321 | R41: 4048 | S41: 4050 | T41: 12146 | U41: 6073 | V41: 52638 | AE41: Yobe | AF41: 13 | AG41: 2 | AH41: 3 | AI41: 5 | AJ41: 1 | AK41: 24 | AW41: Yobe | AX41: 5400 | AY41: 450 | AZ41: 600 | BA41: 2150 | BB41: 100 | BC41: 8700
P42: Grand Total | Q42: 1575038 | R42: 236858 | S42: 433244 | T42: 680233 | U42: 111353 | V42: 3036726 | AE42: Zamfara | AF42: 13 | AG42: 2 | AH42: 2 | AI42: 6 | AJ42: 3 | AK42: 26 | AW42: Zamfara | AX42: 3200 | AY42: 950 | AZ42: 350 | BA42: 2350 | BB42: 2500 | BC42: 9350
AE43: Grand Total | AF43: 778 | AG43: 117 | AH43: 214 | AI43: 336 | AJ43: 55 | AK43: 1500 | AW43: Grand Total | AX43: 269150 | AY43: 37050 | AZ43: 72350 | BA43: 110150 | BB43: 19950 | BC43: 508650

Sheet FUTZAV Dashboard

Sheet Summary
A1: FUTZAV | Poultry Sales Analysis
A4: Metric | B4: Value | F4: Sales channel | G4: Orders | H4: Order share
A5: Orders | B5: =COUNTA('Poultry dataset'!A2:A1501) -> 1500 | F5: WhatsApp | G5: =COUNTIF('Poultry dataset'!$V$2:$V$1501,F5) -> 485 | H5: =G5/$B$5 -> 0.32333333
A6: Chicks ordered | B6: =SUM('Poultry dataset'!E2:E1501) -> 508650 | F6: Phone Call | G6: =COUNTIF('Poultry dataset'!$V$2:$V$1501,F6) -> 246 | H6: =G6/$B$5 -> 0.164
A7: Revenue (NGN) | B7: =SUM('Poultry dataset'!H2:H1501) -> 5.0868969e+08 | F7: Reseller | G7: =COUNTIF('Poultry dataset'!$V$2:$V$1501,F7) -> 222 | H7: =G7/$B$5 -> 0.148
A8: Net profit (NGN) | B8: =SUM('Poultry dataset'!AA2:AA1501) -> 79509966 | F8: Referral | G8: =COUNTIF('Poultry dataset'!$V$2:$V$1501,F8) -> 197 | H8: =G8/$B$5 -> 0.13133333
A9: Net profit source field (NGN) | B9: =SUM('Poultry dataset'!Q2:Q1501) -> 79509966 | F9: Social Media | G9: =COUNTIF('Poultry dataset'!$V$2:$V$1501,F9) -> 190 | H9: =G9/$B$5 -> 0.12666667
A10: Profit reconciliation (NGN) | B10: =SUM('Poultry dataset'!AC2:AC1501) -> 0 | F10: Walk-in | G10: =COUNTIF('Poultry dataset'!$V$2:$V$1501,F10) -> 160 | H10: =G10/$B$5 -> 0.10666667
A13: Product volume | B13: Chicks ordered | C13: Share of total | D13: Orders | F13: Region | G13: Chicks ordered | H13: Order count
A14: Broiler DOC | B14: =SUMIF('Poultry dataset'!$D$2:$D$1501,A14,'Poultry dataset'!$E$2:$E$1501) -> 269150 | C14: =B14/$B$6 -> 0.52914578 | D14: =COUNTIF('Poultry dataset'!$D$2:$D$1501,A14) -> 778 | F14: South West | G14: =SUMIF('Poultry dataset'!$Y$2:$Y$1501,F14,'Poultry dataset'!$E$2:$E$1501) -> 177200 | H14: =COUNTIF('Poultry dataset'!$Y$2:$Y$1501,F14) -> 520
A15: Pullet DOC | B15: =SUMIF('Poultry dataset'!$D$2:$D$1501,A15,'Poultry dataset'!$E$2:$E$1501) -> 110150 | C15: =B15/$B$6 -> 0.21655362 | D15: =COUNTIF('Poultry dataset'!$D$2:$D$1501,A15) -> 336 | F15: South East | G15: =SUMIF('Poultry dataset'!$Y$2:$Y$1501,F15,'Poultry dataset'!$E$2:$E$1501) -> 76150 | H15: =COUNTIF('Poultry dataset'!$Y$2:$Y$1501,F15) -> 222
A16: Noiler DOC | B16: =SUMIF('Poultry dataset'!$D$2:$D$1501,A16,'Poultry dataset'!$E$2:$E$1501) -> 72350 | C16: =B16/$B$6 -> 0.14223926 | D16: =COUNTIF('Poultry dataset'!$D$2:$D$1501,A16) -> 214 | F16: North Central | G16: =SUMIF('Poultry dataset'!$Y$2:$Y$1501,F16,'Poultry dataset'!$E$2:$E$1501) -> 76050 | H16: =COUNTIF('Poultry dataset'!$Y$2:$Y$1501,F16) -> 219
A17: Cockerel DOC | B17: =SUMIF('Poultry dataset'!$D$2:$D$1501,A17,'Poultry dataset'!$E$2:$E$1501) -> 37050 | C17: =B17/$B$6 -> 0.07283987 | D17: =COUNTIF('Poultry dataset'!$D$2:$D$1501,A17) -> 117 | F17: North West | G17: =SUMIF('Poultry dataset'!$Y$2:$Y$1501,F17,'Poultry dataset'!$E$2:$E$1501) -> 70700 | H17: =COUNTIF('Poultry dataset'!$Y$2:$Y$1501,F17) -> 210
A18: Turkey Poults | B18: =SUMIF('Poultry dataset'!$D$2:$D$1501,A18,'Poultry dataset'!$E$2:$E$1501) -> 19950 | C18: =B18/$B$6 -> 0.039221469 | D18: =COUNTIF('Poultry dataset'!$D$2:$D$1501,A18) -> 55 | F18: South South | G18: =SUMIF('Poultry dataset'!$Y$2:$Y$1501,F18,'Poultry dataset'!$E$2:$E$1501) -> 64050 | H18: =COUNTIF('Poultry dataset'!$Y$2:$Y$1501,F18) -> 200
F19: North East | G19: =SUMIF('Poultry dataset'!$Y$2:$Y$1501,F19,'Poultry dataset'!$E$2:$E$1501) -> 44500 | H19: =COUNTIF('Poultry dataset'!$Y$2:$Y$1501,F19) -> 129

Sheet DAX Measures
A3: Measure / object | B3: DAX expression | C3: Purpose
A4: Total Orders | B4: Total Orders = COUNTROWS('Sales') | C4: Number of order rows in current filter context
A5: Total Chicks Ordered | B5: Total Chicks Ordered = SUM('Sales'[Quantity_Ordered]) | C5: Ordered volume
A6: Total Revenue (NGN) | B6: Total Revenue (NGN) = SUM('Sales'[Revenue_NGN]) | C6: Revenue field total
A7: Total Cost (NGN) | B7: Total Cost (NGN) = SUM('Sales'[Total_Cost_NGN]) | C7: Total recorded cost
A8: Gross Profit (NGN) | B8: Gross Profit (NGN) = SUM('Sales'[Gross_Profit_NGN]) | C8: Gross profit field total
A9: Net Profit (NGN) | B9: Net Profit (NGN) = SUM('Sales'[Computed_Net_Profit_NGN]) | C9: Uses the calculated row-level column; matches slide total
A10: Source Net Profit (NGN) | B10: Source Net Profit (NGN) = SUM('Sales'[Net_Profit_NGN]) | C10: Reconciliation against source field
A11: Net Profit Reconciliation | B11: Net Profit Reconciliation (NGN) = [Net Profit (NGN)] - [Source Net Profit (NGN)] | C11: Should be 0
A12: Net Profit Margin | B12: Net Profit Margin = DIVIDE([Net Profit (NGN)], [Total Revenue (NGN)]) | C12: Net profit divided by revenue
A13: Outstanding Balance | B13: Outstanding Balance (NGN) = SUM('Sales'[Balance_Due_NGN]) | C13: Remaining customer balances
A14: Average Order Value | B14: Average Order Value (NGN) = DIVIDE([Total Revenue (NGN)], [Total Orders]) | C14: Average revenue per order row
... A22: Calendar month name | B22: Calendar Month = FORMAT(Calendar[Date], "MMMM") | C22: Calculated column in Calendar table
